{"results": [{"alternatives": [{}], "resultEndTime": "0.750s", "languageCode": "en-us"}, {"alternatives": [{}], "resultEndTime": "12.760s", "languageCode": "en-us"}, {"alternatives": [{}], "resultEndTime": "20.810s", "languageCode": "en-us"}, {"alternatives": [{}], "resultEndTime": "48.800s", "languageCode": "en-us"}, {"alternatives": [{}], "resultEndTime": "60.740s", "languageCode": "en-us"}, {"alternatives": [{}], "resultEndTime": "71.750s", "languageCode": "en-us"}, {"alternatives": [{}], "resultEndTime": "73.310s", "languageCode": "en-us"}, {"alternatives": [{}], "resultEndTime": "79.510s", "languageCode": "en-us"}, {"alternatives": [{}], "resultEndTime": "80.970s", "languageCode": "en-us"}, {"alternatives": [{}], "resultEndTime": "84.660s", "languageCode": "en-us"}, {"alternatives": [{}], "resultEndTime": "90.420s", "languageCode": "en-us"}, {"alternatives": [{}], "resultEndTime": "94.140s", "languageCode": "en-us"}, {"alternatives": [{}], "resultEndTime": "98.280s", "languageCode": "en-us"}, {"alternatives": [{}], "resultEndTime": "99.680s", "languageCode": "en-us"}, {"alternatives": [{}], "resultEndTime": "103.120s", "languageCode": "en-us"}, {"alternatives": [{}], "resultEndTime": "105.360s", "languageCode": "en-us"}, {"alternatives": [{}], "resultEndTime": "106.840s", "languageCode": "en-us"}, {"alternatives": [{}], "resultEndTime": "109.790s", "languageCode": "en-us"}, {"alternatives": [{}], "resultEndTime": "111.250s", "languageCode": "en-us"}, {"alternatives": [{}], "resultEndTime": "113.260s", "languageCode": "en-us"}, {"alternatives": [{}], "resultEndTime": "118.520s", "languageCode": "en-us"}, {"alternatives": [{}], "resultEndTime": "121.310s", "languageCode": "en-us"}, {"alternatives": [{}], "resultEndTime": "125.750s", "languageCode": "en-us"}, {"alternatives": [{}], "resultEndTime": "126.910s", "languageCode": "en-us"}, {"alternatives": [{}], "resultEndTime": "142.370s", "languageCode": "en-us"}, {"alternatives": [{}], "resultEndTime": "146.060s", "languageCode": "en-us"}, {"alternatives": [{}], "resultEndTime": "151.440s", "languageCode": "en-us"}, {"alternatives": [{}], "resultEndTime": "153.700s", "languageCode": "en-us"}, {"alternatives": [{}], "resultEndTime": "157.750s", "languageCode": "en-us"}, {"alternatives": [{}], "resultEndTime": "163.160s", "languageCode": "en-us"}, {"alternatives": [{}], "resultEndTime": "164.630s", "languageCode": "en-us"}, {"alternatives": [{}], "resultEndTime": "167.190s", "languageCode": "en-us"}, {"alternatives": [{}], "resultEndTime": "180.200s", "languageCode": "en-us"}, {"alternatives": [{}], "resultEndTime": "192.720s", "languageCode": "en-us"}, {"alternatives": [{}], "resultEndTime": "211.550s", "languageCode": "en-us"}, {"alternatives": [{}], "resultEndTime": "215.140s", "languageCode": "en-us"}, {"alternatives": [{}], "resultEndTime": "215.890s", "languageCode": "en-us"}, {"alternatives": [{}], "resultEndTime": "221.620s", "languageCode": "en-us"}, {"alternatives": [{}], "resultEndTime": "226.360s", "languageCode": "en-us"}, {"alternatives": [{}], "resultEndTime": "228.910s", "languageCode": "en-us"}, {"alternatives": [{}], "resultEndTime": "233.350s", "languageCode": "en-us"}, {"alternatives": [{}], "resultEndTime": "238.480s", "languageCode": "en-us"}, {"alternatives": [{}], "resultEndTime": "239.920s", "languageCode": "en-us"}, {"alternatives": [{}], "resultEndTime": "248.590s", "languageCode": "en-us"}, {"alternatives": [{}], "resultEndTime": "251.820s", "languageCode": "en-us"}, {"alternatives": [{}], "resultEndTime": "261.130s", "languageCode": "en-us"}, {"alternatives": [{}], "resultEndTime": "267.690s", "languageCode": "en-us"}, {"alternatives": [{}], "resultEndTime": "274.140s", "languageCode": "en-us"}, {"alternatives": [{}], "resultEndTime": "275.360s", "languageCode": "en-us"}, {"alternatives": [{}], "resultEndTime": "279s", "languageCode": "en-us"}, {"alternatives": [{}], "resultEndTime": "287.860s", "languageCode": "en-us"}, {"alternatives": [{}], "resultEndTime": "289.900s", "languageCode": "en-us"}, {"alternatives": [{}], "resultEndTime": "296.160s", "languageCode": "en-us"}, {"alternatives": [{}], "resultEndTime": "306.400s", "languageCode": "en-us"}, {"alternatives": [{}], "resultEndTime": "311.190s", "languageCode": "en-us"}, {"alternatives": [{}], "resultEndTime": "320.460s", "languageCode": "en-us"}, {"alternatives": [{}], "resultEndTime": "322.620s", "languageCode": "en-us"}, {"alternatives": [{}], "resultEndTime": "324.870s", "languageCode": "en-us"}, {"alternatives": [{}], "resultEndTime": "327.770s", "languageCode": "en-us"}, {"alternatives": [{}], "resultEndTime": "336.610s", "languageCode": "en-us"}, {"alternatives": [{}], "resultEndTime": "339.330s", "languageCode": "en-us"}, {"alternatives": [{}], "resultEndTime": "346.840s", "languageCode": "en-us"}, {"alternatives": [{}], "resultEndTime": "352.240s", "languageCode": "en-us"}, {"alternatives": [{}], "resultEndTime": "361.800s", "languageCode": "en-us"}, {"alternatives": [{}], "resultEndTime": "369.240s", "languageCode": "en-us"}, {"alternatives": [{}], "resultEndTime": "376.240s", "languageCode": "en-us"}, {"alternatives": [{}], "resultEndTime": "383.830s", "languageCode": "en-us"}, {"alternatives": [{}], "resultEndTime": "398.240s", "languageCode": "en-us"}, {"alternatives": [{}], "resultEndTime": "402.590s", "languageCode": "en-us"}, {"alternatives": [{}], "resultEndTime": "415.020s", "languageCode": "en-us"}, {"alternatives": [{}], "resultEndTime": "421.290s", "languageCode": "en-us"}, {"alternatives": [{}], "resultEndTime": "425.640s", "languageCode": "en-us"}, {"alternatives": [{}], "resultEndTime": "436.470s", "languageCode": "en-us"}, {"alternatives": [{}], "resultEndTime": "443.730s", "languageCode": "en-us"}, {"alternatives": [{}], "resultEndTime": "449s", "languageCode": "en-us"}, {"alternatives": [{}], "resultEndTime": "451.610s", "languageCode": "en-us"}, {"alternatives": [{}], "resultEndTime": "454.900s", "languageCode": "en-us"}, {"alternatives": [{}], "resultEndTime": "459.370s", "languageCode": "en-us"}, {"alternatives": [{}], "resultEndTime": "467.190s", "languageCode": "en-us"}, {"alternatives": [{}], "resultEndTime": "469.950s", "languageCode": "en-us"}, {"alternatives": [{}], "resultEndTime": "476.530s", "languageCode": "en-us"}, {"alternatives": [{}], "resultEndTime": "481.220s", "languageCode": "en-us"}, {"alternatives": [{}], "resultEndTime": "483.420s", "languageCode": "en-us"}, {"alternatives": [{}], "resultEndTime": "489.460s", "languageCode": "en-us"}, {"alternatives": [{}], "resultEndTime": "491.790s", "languageCode": "en-us"}, {"alternatives": [{}], "resultEndTime": "498.460s", "languageCode": "en-us"}, {"alternatives": [{}], "resultEndTime": "509.130s", "languageCode": "en-us"}, {"alternatives": [{}], "resultEndTime": "509.850s", "languageCode": "en-us"}, {"alternatives": [{}], "resultEndTime": "512.800s", "languageCode": "en-us"}, {"alternatives": [{}], "resultEndTime": "518.420s", "languageCode": "en-us"}, {"alternatives": [{}], "resultEndTime": "528.450s", "languageCode": "en-us"}, {"alternatives": [{}], "resultEndTime": "531.790s", "languageCode": "en-us"}, {"alternatives": [{}], "resultEndTime": "546.680s", "languageCode": "en-us"}, {"alternatives": [{}], "resultEndTime": "548.060s", "languageCode": "en-us"}, {"alternatives": [{}], "resultEndTime": "552.130s", "languageCode": "en-us"}, {"alternatives": [{}], "resultEndTime": "555.830s", "languageCode": "en-us"}, {"alternatives": [{}], "resultEndTime": "561.020s", "languageCode": "en-us"}, {"alternatives": [{}], "resultEndTime": "563.690s", "languageCode": "en-us"}, {"alternatives": [{}], "resultEndTime": "566.400s", "languageCode": "en-us"}, {"alternatives": [{}], "resultEndTime": "572.400s", "languageCode": "en-us"}, {"alternatives": [{}], "resultEndTime": "576.210s", "languageCode": "en-us"}, {"alternatives": [{}], "resultEndTime": "577.320s", "languageCode": "en-us"}, {"alternatives": [{}], "resultEndTime": "582.340s", "languageCode": "en-us"}, {"alternatives": [{}], "resultEndTime": "584.920s", "languageCode": "en-us"}, {"alternatives": [{}], "resultEndTime": "588.840s", "languageCode": "en-us"}, {"alternatives": [{}], "resultEndTime": "599.600s", "languageCode": "en-us"}, {"alternatives": [{}], "resultEndTime": "606.780s", "languageCode": "en-us"}, {"alternatives": [{}], "resultEndTime": "610.280s", "languageCode": "en-us"}, {"alternatives": [{}], "resultEndTime": "614.840s", "languageCode": "en-us"}, {"alternatives": [{}], "resultEndTime": "622.250s", "languageCode": "en-us"}, {"alternatives": [{}], "resultEndTime": "623.810s", "languageCode": "en-us"}, {"alternatives": [{}], "resultEndTime": "631.160s", "languageCode": "en-us"}, {"alternatives": [{}], "resultEndTime": "632.410s", "languageCode": "en-us"}, {"alternatives": [{}], "resultEndTime": "637.830s", "languageCode": "en-us"}, {"alternatives": [{}], "resultEndTime": "645.090s", "languageCode": "en-us"}, {"alternatives": [{}], "resultEndTime": "652.500s", "languageCode": "en-us"}, {"alternatives": [{}], "resultEndTime": "653.970s", "languageCode": "en-us"}, {"alternatives": [{}], "resultEndTime": "656.330s", "languageCode": "en-us"}, {"alternatives": [{}], "resultEndTime": "660.950s", "languageCode": "en-us"}, {"alternatives": [{}], "resultEndTime": "663.230s", "languageCode": "en-us"}, {"alternatives": [{}], "resultEndTime": "665.790s", "languageCode": "en-us"}, {"alternatives": [{}], "resultEndTime": "668.820s", "languageCode": "en-us"}, {"alternatives": [{}], "resultEndTime": "671.610s", "languageCode": "en-us"}, {"alternatives": [{}], "resultEndTime": "678.390s", "languageCode": "en-us"}, {"alternatives": [{}], "resultEndTime": "683s", "languageCode": "en-us"}, {"alternatives": [{}], "resultEndTime": "687.100s", "languageCode": "en-us"}, {"alternatives": [{}], "resultEndTime": "689.140s", "languageCode": "en-us"}, {"alternatives": [{}], "resultEndTime": "691.610s", "languageCode": "en-us"}, {"alternatives": [{}], "resultEndTime": "697.200s", "languageCode": "en-us"}, {"alternatives": [{}], "resultEndTime": "699.260s", "languageCode": "en-us"}, {"alternatives": [{}], "resultEndTime": "703.060s", "languageCode": "en-us"}, {"alternatives": [{}], "resultEndTime": "706.600s", "languageCode": "en-us"}, {"alternatives": [{}], "resultEndTime": "719.040s", "languageCode": "en-us"}, {"alternatives": [{}], "resultEndTime": "722.780s", "languageCode": "en-us"}, {"alternatives": [{}], "resultEndTime": "725.090s", "languageCode": "en-us"}, {"alternatives": [{}], "resultEndTime": "729.180s", "languageCode": "en-us"}, {"alternatives": [{}], "resultEndTime": "730.810s", "languageCode": "en-us"}, {"alternatives": [{}], "resultEndTime": "732.800s", "languageCode": "en-us"}, {"alternatives": [{}], "resultEndTime": "736.340s", "languageCode": "en-us"}, {"alternatives": [{}], "resultEndTime": "739.440s", "languageCode": "en-us"}, {"alternatives": [{}], "resultEndTime": "742.660s", "languageCode": "en-us"}, {"alternatives": [{}], "resultEndTime": "749.440s", "languageCode": "en-us"}, {"alternatives": [{}], "resultEndTime": "752.270s", "languageCode": "en-us"}, {"alternatives": [{}], "resultEndTime": "755.650s", "languageCode": "en-us"}, {"alternatives": [{}], "resultEndTime": "759.580s", "languageCode": "en-us"}, {"alternatives": [{}], "resultEndTime": "768.170s", "languageCode": "en-us"}, {"alternatives": [{}], "resultEndTime": "769.730s", "languageCode": "en-us"}, {"alternatives": [{}], "resultEndTime": "771.540s", "languageCode": "en-us"}, {"alternatives": [{}], "resultEndTime": "774.930s", "languageCode": "en-us"}, {"alternatives": [{}], "resultEndTime": "776.810s", "languageCode": "en-us"}, {"alternatives": [{}], "resultEndTime": "781.010s", "languageCode": "en-us"}, {"alternatives": [{}], "resultEndTime": "790.730s", "languageCode": "en-us"}, {"alternatives": [{}], "resultEndTime": "793.550s", "languageCode": "en-us"}, {"alternatives": [{}], "resultEndTime": "798.260s", "languageCode": "en-us"}, {"alternatives": [{}], "resultEndTime": "806.750s", "languageCode": "en-us"}, {"alternatives": [{}], "resultEndTime": "810.480s", "languageCode": "en-us"}, {"alternatives": [{}], "resultEndTime": "812.960s", "languageCode": "en-us"}, {"alternatives": [{}], "resultEndTime": "819.580s", "languageCode": "en-us"}, {"alternatives": [{}], "resultEndTime": "821.880s", "languageCode": "en-us"}, {"alternatives": [{}], "resultEndTime": "824.980s", "languageCode": "en-us"}, {"alternatives": [{}], "resultEndTime": "827.950s", "languageCode": "en-us"}, {"alternatives": [{}], "resultEndTime": "831.020s", "languageCode": "en-us"}, {"alternatives": [{}], "resultEndTime": "833.740s", "languageCode": "en-us"}, {"alternatives": [{}], "resultEndTime": "835.220s", "languageCode": "en-us"}, {"alternatives": [{}], "resultEndTime": "838.550s", "languageCode": "en-us"}, {"alternatives": [{}], "resultEndTime": "842.770s", "languageCode": "en-us"}, {"alternatives": [{}], "resultEndTime": "847.090s", "languageCode": "en-us"}, {"alternatives": [{}], "resultEndTime": "849.250s", "languageCode": "en-us"}, {"alternatives": [{}], "resultEndTime": "851.560s", "languageCode": "en-us"}, {"alternatives": [{}], "resultEndTime": "856.860s", "languageCode": "en-us"}, {"alternatives": [{}], "resultEndTime": "862.520s", "languageCode": "en-us"}, {"alternatives": [{}], "resultEndTime": "863.680s", "languageCode": "en-us"}, {"alternatives": [{}], "resultEndTime": "867.520s", "languageCode": "en-us"}, {"alternatives": [{}], "resultEndTime": "870.370s", "languageCode": "en-us"}, {"alternatives": [{}], "resultEndTime": "872.390s", "languageCode": "en-us"}, {"alternatives": [{}], "resultEndTime": "875.220s", "languageCode": "en-us"}, {"alternatives": [{}], "resultEndTime": "879.470s", "languageCode": "en-us"}, {"alternatives": [{}], "resultEndTime": "881.290s", "languageCode": "en-us"}, {"alternatives": [{}], "resultEndTime": "885.070s", "languageCode": "en-us"}, {"alternatives": [{}], "resultEndTime": "887.580s", "languageCode": "en-us"}, {"alternatives": [{}], "resultEndTime": "892.630s", "languageCode": "en-us"}, {"alternatives": [{}], "resultEndTime": "895.690s", "languageCode": "en-us"}, {"alternatives": [{}], "resultEndTime": "897.820s", "languageCode": "en-us"}, {"alternatives": [{}], "resultEndTime": "900.470s", "languageCode": "en-us"}, {"alternatives": [{}], "resultEndTime": "903.470s", "languageCode": "en-us"}, {"alternatives": [{}], "resultEndTime": "907.390s", "languageCode": "en-us"}, {"alternatives": [{}], "resultEndTime": "909.680s", "languageCode": "en-us"}, {"alternatives": [{}], "resultEndTime": "912.350s", "languageCode": "en-us"}, {"alternatives": [{}], "resultEndTime": "916.370s", "languageCode": "en-us"}, {"alternatives": [{}], "resultEndTime": "921.290s", "languageCode": "en-us"}, {"alternatives": [{}], "resultEndTime": "924.580s", "languageCode": "en-us"}, {"alternatives": [{}], "resultEndTime": "926.480s", "languageCode": "en-us"}, {"alternatives": [{}], "resultEndTime": "936.050s", "languageCode": "en-us"}, {"alternatives": [{}], "resultEndTime": "939.020s", "languageCode": "en-us"}, {"alternatives": [{}], "resultEndTime": "947.540s", "languageCode": "en-us"}, {"alternatives": [{}], "resultEndTime": "950.160s", "languageCode": "en-us"}, {"alternatives": [{}], "resultEndTime": "963.890s", "languageCode": "en-us"}, {"alternatives": [{}], "resultEndTime": "967.060s", "languageCode": "en-us"}, {"alternatives": [{}], "resultEndTime": "974.220s", "languageCode": "en-us"}, {"alternatives": [{}], "resultEndTime": "977.080s", "languageCode": "en-us"}, {"alternatives": [{}], "resultEndTime": "981.190s", "languageCode": "en-us"}, {"alternatives": [{}], "resultEndTime": "983.280s", "languageCode": "en-us"}, {"alternatives": [{}], "resultEndTime": "986.960s", "languageCode": "en-us"}, {"alternatives": [{}], "resultEndTime": "990.770s", "languageCode": "en-us"}, {"alternatives": [{}], "resultEndTime": "999.630s", "languageCode": "en-us"}, {"alternatives": [{}], "resultEndTime": "1008.980s", "languageCode": "en-us"}, {"alternatives": [{}], "resultEndTime": "1018.280s", "languageCode": "en-us"}, {"alternatives": [{}], "resultEndTime": "1022.790s", "languageCode": "en-us"}, {"alternatives": [{}], "resultEndTime": "1029.250s", "languageCode": "en-us"}, {"alternatives": [{}], "resultEndTime": "1036.810s", "languageCode": "en-us"}, {"alternatives": [{}], "resultEndTime": "1039.910s", "languageCode": "en-us"}, {"alternatives": [{}], "resultEndTime": "1050.710s", "languageCode": "en-us"}, {"alternatives": [{}], "resultEndTime": "1060.730s", "languageCode": "en-us"}, {"alternatives": [{}], "resultEndTime": "1064.590s", "languageCode": "en-us"}, {"alternatives": [{}], "resultEndTime": "1067.830s", "languageCode": "en-us"}, {"alternatives": [{}], "resultEndTime": "1072.760s", "languageCode": "en-us"}, {"alternatives": [{}], "resultEndTime": "1076.200s", "languageCode": "en-us"}, {"alternatives": [{}], "resultEndTime": "1077.700s", "languageCode": "en-us"}, {"alternatives": [{}], "resultEndTime": "1087.520s", "languageCode": "en-us"}, {"alternatives": [{}], "resultEndTime": "1089.560s", "languageCode": "en-us"}, {"alternatives": [{}], "resultEndTime": "1110.560s", "languageCode": "en-us"}, {"alternatives": [{}], "resultEndTime": "1117.370s", "languageCode": "en-us"}, {"alternatives": [{}], "resultEndTime": "1127.320s", "languageCode": "en-us"}, {"alternatives": [{}], "resultEndTime": "1130.210s", "languageCode": "en-us"}, {"alternatives": [{}], "resultEndTime": "1132.210s", "languageCode": "en-us"}, {"alternatives": [{}], "resultEndTime": "1134.860s", "languageCode": "en-us"}, {"alternatives": [{}], "resultEndTime": "1138.690s", "languageCode": "en-us"}, {"alternatives": [{}], "resultEndTime": "1143.660s", "languageCode": "en-us"}, {"alternatives": [{}], "resultEndTime": "1148.920s", "languageCode": "en-us"}, {"alternatives": [{}], "resultEndTime": "1152.530s", "languageCode": "en-us"}, {"alternatives": [{}], "resultEndTime": "1155.670s", "languageCode": "en-us"}, {"alternatives": [{}], "resultEndTime": "1158.090s", "languageCode": "en-us"}, {"alternatives": [{}], "resultEndTime": "1160.700s", "languageCode": "en-us"}, {"alternatives": [{}], "resultEndTime": "1163.500s", "languageCode": "en-us"}, {"alternatives": [{}], "resultEndTime": "1165.520s", "languageCode": "en-us"}, {"alternatives": [{}], "resultEndTime": "1167.420s", "languageCode": "en-us"}, {"alternatives": [{}], "resultEndTime": "1168.990s", "languageCode": "en-us"}, {"alternatives": [{}], "resultEndTime": "1173.210s", "languageCode": "en-us"}, {"alternatives": [{}], "resultEndTime": "1175.060s", "languageCode": "en-us"}, {"alternatives": [{}], "resultEndTime": "1178.450s", "languageCode": "en-us"}, {"alternatives": [{}], "resultEndTime": "1182.440s", "languageCode": "en-us"}, {"alternatives": [{}], "resultEndTime": "1184.630s", "languageCode": "en-us"}, {"alternatives": [{}], "resultEndTime": "1186.430s", "languageCode": "en-us"}, {"alternatives": [{}], "resultEndTime": "1189.370s", "languageCode": "en-us"}, {"alternatives": [{}], "resultEndTime": "1196.970s", "languageCode": "en-us"}, {"alternatives": [{}], "resultEndTime": "1198.340s", "languageCode": "en-us"}, {"alternatives": [{}], "resultEndTime": "1203.630s", "languageCode": "en-us"}, {"alternatives": [{}], "resultEndTime": "1206.920s", "languageCode": "en-us"}, {"alternatives": [{}], "resultEndTime": "1208.270s", "languageCode": "en-us"}, {"alternatives": [{}], "resultEndTime": "1213.780s", "languageCode": "en-us"}, {"alternatives": [{}], "resultEndTime": "1215.360s", "languageCode": "en-us"}, {"alternatives": [{}], "resultEndTime": "1218.790s", "languageCode": "en-us"}, {"alternatives": [{}], "resultEndTime": "1221.920s", "languageCode": "en-us"}, {"alternatives": [{}], "resultEndTime": "1225.550s", "languageCode": "en-us"}, {"alternatives": [{}], "resultEndTime": "1234.840s", "languageCode": "en-us"}, {"alternatives": [{}], "resultEndTime": "1235.560s", "languageCode": "en-us"}, {"alternatives": [{}], "resultEndTime": "1240.970s", "languageCode": "en-us"}, {"alternatives": [{}], "resultEndTime": "1244.440s", "languageCode": "en-us"}, {"alternatives": [{}], "resultEndTime": "1247.100s", "languageCode": "en-us"}, {"alternatives": [{}], "resultEndTime": "1248.670s", "languageCode": "en-us"}, {"alternatives": [{}], "resultEndTime": "1250.930s", "languageCode": "en-us"}, {"alternatives": [{}], "resultEndTime": "1255.460s", "languageCode": "en-us"}, {"alternatives": [{}], "resultEndTime": "1271.600s", "languageCode": "en-us"}, {"alternatives": [{}], "resultEndTime": "1275.890s", "languageCode": "en-us"}, {"alternatives": [{}], "resultEndTime": "1277.970s", "languageCode": "en-us"}, {"alternatives": [{}], "resultEndTime": "1283.510s", "languageCode": "en-us"}, {"alternatives": [{}], "resultEndTime": "1286.600s", "languageCode": "en-us"}, {"alternatives": [{}], "resultEndTime": "1289.700s", "languageCode": "en-us"}, {"alternatives": [{}], "resultEndTime": "1291.800s", "languageCode": "en-us"}, {"alternatives": [{}], "resultEndTime": "1293.530s", "languageCode": "en-us"}, {"alternatives": [{}], "resultEndTime": "1295.520s", "languageCode": "en-us"}, {"alternatives": [{}], "resultEndTime": "1304.270s", "languageCode": "en-us"}, {"alternatives": [{}], "resultEndTime": "1307.220s", "languageCode": "en-us"}, {"alternatives": [{}], "resultEndTime": "1308.060s", "languageCode": "en-us"}, {"alternatives": [{}], "resultEndTime": "1312.680s", "languageCode": "en-us"}, {"alternatives": [{}], "resultEndTime": "1316.680s", "languageCode": "en-us"}, {"alternatives": [{}], "resultEndTime": "1322.960s", "languageCode": "en-us"}, {"alternatives": [{}], "resultEndTime": "1324.780s", "languageCode": "en-us"}, {"alternatives": [{}], "resultEndTime": "1330.660s", "languageCode": "en-us"}, {"alternatives": [{}], "resultEndTime": "1340.870s", "languageCode": "en-us"}, {"alternatives": [{}], "resultEndTime": "1344.070s", "languageCode": "en-us"}, {"alternatives": [{}], "resultEndTime": "1347.450s", "languageCode": "en-us"}, {"alternatives": [{}], "resultEndTime": "1351.430s", "languageCode": "en-us"}, {"alternatives": [{}], "resultEndTime": "1355.880s", "languageCode": "en-us"}, {"alternatives": [{}], "resultEndTime": "1362.350s", "languageCode": "en-us"}, {"alternatives": [{}], "resultEndTime": "1363.760s", "languageCode": "en-us"}, {"alternatives": [{}], "resultEndTime": "1366.960s", "languageCode": "en-us"}, {"alternatives": [{}], "resultEndTime": "1371.670s", "languageCode": "en-us"}, {"alternatives": [{}], "resultEndTime": "1375.030s", "languageCode": "en-us"}, {"alternatives": [{}], "resultEndTime": "1378.150s", "languageCode": "en-us"}, {"alternatives": [{}], "resultEndTime": "1381.060s", "languageCode": "en-us"}, {"alternatives": [{}], "resultEndTime": "1382.530s", "languageCode": "en-us"}, {"alternatives": [{}], "resultEndTime": "1390.870s", "languageCode": "en-us"}, {"alternatives": [{}], "resultEndTime": "1397.190s", "languageCode": "en-us"}, {"alternatives": [{}], "resultEndTime": "1403.350s", "languageCode": "en-us"}, {"alternatives": [{}], "resultEndTime": "1405.250s", "languageCode": "en-us"}, {"alternatives": [{}], "resultEndTime": "1409.350s", "languageCode": "en-us"}, {"alternatives": [{}], "resultEndTime": "1415.480s", "languageCode": "en-us"}, {"alternatives": [{}], "resultEndTime": "1418.150s", "languageCode": "en-us"}, {"alternatives": [{}], "resultEndTime": "1424.380s", "languageCode": "en-us"}, {"alternatives": [{}], "resultEndTime": "1426.500s", "languageCode": "en-us"}, {"alternatives": [{}], "resultEndTime": "1429.050s", "languageCode": "en-us"}, {"alternatives": [{}], "resultEndTime": "1433.640s", "languageCode": "en-us"}, {"alternatives": [{}], "resultEndTime": "1435.930s", "languageCode": "en-us"}, {"alternatives": [{}], "resultEndTime": "1443.040s", "languageCode": "en-us"}, {"alternatives": [{}], "resultEndTime": "1451.510s", "languageCode": "en-us"}, {"alternatives": [{}], "resultEndTime": "1452.110s", "languageCode": "en-us"}, {"alternatives": [{}], "resultEndTime": "1454.470s", "languageCode": "en-us"}, {"alternatives": [{}], "resultEndTime": "1457.950s", "languageCode": "en-us"}, {"alternatives": [{}], "resultEndTime": "1459.720s", "languageCode": "en-us"}, {"alternatives": [{}], "resultEndTime": "1462.640s", "languageCode": "en-us"}, {"alternatives": [{}], "resultEndTime": "1466.540s", "languageCode": "en-us"}, {"alternatives": [{}], "resultEndTime": "1475s", "languageCode": "en-us"}, {"alternatives": [{}], "resultEndTime": "1477.860s", "languageCode": "en-us"}, {"alternatives": [{}], "resultEndTime": "1482.640s", "languageCode": "en-us"}, {"alternatives": [{}], "resultEndTime": "1488.190s", "languageCode": "en-us"}, {"alternatives": [{}], "resultEndTime": "1500.910s", "languageCode": "en-us"}, {"alternatives": [{}], "resultEndTime": "1513.270s", "languageCode": "en-us"}, {"alternatives": [{}], "resultEndTime": "1522.550s", "languageCode": "en-us"}, {"alternatives": [{}], "resultEndTime": "1528.220s", "languageCode": "en-us"}, {"alternatives": [{}], "resultEndTime": "1549.110s", "languageCode": "en-us"}, {"alternatives": [{}], "resultEndTime": "1550.460s", "languageCode": "en-us"}, {"alternatives": [{}], "resultEndTime": "1554.050s", "languageCode": "en-us"}, {"alternatives": [{}], "resultEndTime": "1560.400s", "languageCode": "en-us"}, {"alternatives": [{}], "resultEndTime": "1565.330s", "languageCode": "en-us"}, {"alternatives": [{}], "resultEndTime": "1572.820s", "languageCode": "en-us"}, {"alternatives": [{}], "resultEndTime": "1580.870s", "languageCode": "en-us"}, {"alternatives": [{}], "resultEndTime": "1584.500s", "languageCode": "en-us"}, {"alternatives": [{}], "resultEndTime": "1607.270s", "languageCode": "en-us"}, {"alternatives": [{}], "resultEndTime": "1614.470s", "languageCode": "en-us"}, {"alternatives": [{}], "resultEndTime": "1621.650s", "languageCode": "en-us"}, {"alternatives": [{}], "resultEndTime": "1633.190s", "languageCode": "en-us"}, {"alternatives": [{}], "resultEndTime": "1638.900s", "languageCode": "en-us"}, {"alternatives": [{}], "resultEndTime": "1652.940s", "languageCode": "en-us"}, {"alternatives": [{}], "resultEndTime": "1661.500s", "languageCode": "en-us"}, {"alternatives": [{}], "resultEndTime": "1665.710s", "languageCode": "en-us"}, {"alternatives": [{}], "resultEndTime": "1671.350s", "languageCode": "en-us"}, {"alternatives": [{}], "resultEndTime": "1676.380s", "languageCode": "en-us"}, {"alternatives": [{}], "resultEndTime": "1687.230s", "languageCode": "en-us"}, {"alternatives": [{}], "resultEndTime": "1689.210s", "languageCode": "en-us"}, {"alternatives": [{}], "resultEndTime": "1696.010s", "languageCode": "en-us"}, {"alternatives": [{}], "resultEndTime": "1699.870s", "languageCode": "en-us"}, {"alternatives": [{}], "resultEndTime": "1712.940s", "languageCode": "en-us"}, {"alternatives": [{}], "resultEndTime": "1719.240s", "languageCode": "en-us"}, {"alternatives": [{}], "resultEndTime": "1721.800s", "languageCode": "en-us"}, {"alternatives": [{}], "resultEndTime": "1724.180s", "languageCode": "en-us"}, {"alternatives": [{}], "resultEndTime": "1728.730s", "languageCode": "en-us"}, {"alternatives": [{}], "resultEndTime": "1733.050s", "languageCode": "en-us"}, {"alternatives": [{}], "resultEndTime": "1735.890s", "languageCode": "en-us"}, {"alternatives": [{}], "resultEndTime": "1740.330s", "languageCode": "en-us"}, {"alternatives": [{}], "resultEndTime": "1755.330s", "languageCode": "en-us"}, {"alternatives": [{}], "resultEndTime": "1760.070s", "languageCode": "en-us"}, {"alternatives": [{}], "resultEndTime": "1764.570s", "languageCode": "en-us"}, {"alternatives": [{}], "resultEndTime": "1777.260s", "languageCode": "en-us"}, {"alternatives": [{}], "resultEndTime": "1779.590s", "languageCode": "en-us"}, {"alternatives": [{}], "resultEndTime": "1791.090s", "languageCode": "en-us"}, {"alternatives": [{}], "resultEndTime": "1801.920s", "languageCode": "en-us"}, {"alternatives": [{}], "resultEndTime": "1803.870s", "languageCode": "en-us"}, {"alternatives": [{}], "resultEndTime": "1808.790s", "languageCode": "en-us"}, {"alternatives": [{}], "resultEndTime": "1814.870s", "languageCode": "en-us"}, {"alternatives": [{}], "resultEndTime": "1817.850s", "languageCode": "en-us"}, {"alternatives": [{}], "resultEndTime": "1821.790s", "languageCode": "en-us"}, {"alternatives": [{}], "resultEndTime": "1822.980s", "languageCode": "en-us"}, {"alternatives": [{}], "resultEndTime": "1828.410s", "languageCode": "en-us"}, {"alternatives": [{}], "resultEndTime": "1830.960s", "languageCode": "en-us"}, {"alternatives": [{}], "resultEndTime": "1834.740s", "languageCode": "en-us"}, {"alternatives": [{}], "resultEndTime": "1837.290s", "languageCode": "en-us"}, {"alternatives": [{}], "resultEndTime": "1838.520s", "languageCode": "en-us"}, {"alternatives": [{}], "resultEndTime": "1845.750s", "languageCode": "en-us"}, {"alternatives": [{}], "resultEndTime": "1849.960s", "languageCode": "en-us"}, {"alternatives": [{}], "resultEndTime": "1851.100s", "languageCode": "en-us"}, {"alternatives": [{}], "resultEndTime": "1858.190s", "languageCode": "en-us"}, {"alternatives": [{}], "resultEndTime": "1867.920s", "languageCode": "en-us"}, {"alternatives": [{}], "resultEndTime": "1885.140s", "languageCode": "en-us"}, {"alternatives": [{}], "resultEndTime": "1889.830s", "languageCode": "en-us"}, {"alternatives": [{}], "resultEndTime": "1893.880s", "languageCode": "en-us"}, {"alternatives": [{}], "resultEndTime": "1898.550s", "languageCode": "en-us"}, {"alternatives": [{}], "resultEndTime": "1899.810s", "languageCode": "en-us"}, {"alternatives": [{}], "resultEndTime": "1902.470s", "languageCode": "en-us"}, {"alternatives": [{}], "resultEndTime": "1903.130s", "languageCode": "en-us"}, {"alternatives": [{}], "resultEndTime": "1906.690s", "languageCode": "en-us"}, {"alternatives": [{}], "resultEndTime": "1917.090s", "languageCode": "en-us"}, {"alternatives": [{}], "resultEndTime": "1921.830s", "languageCode": "en-us"}, {"alternatives": [{}], "resultEndTime": "1924.680s", "languageCode": "en-us"}, {"alternatives": [{}], "resultEndTime": "1937.260s", "languageCode": "en-us"}, {"alternatives": [{}], "resultEndTime": "1939.970s", "languageCode": "en-us"}, {"alternatives": [{}], "resultEndTime": "1943.700s", "languageCode": "en-us"}, {"alternatives": [{}], "resultEndTime": "1949.750s", "languageCode": "en-us"}, {"alternatives": [{}], "resultEndTime": "1951.420s", "languageCode": "en-us"}, {"alternatives": [{}], "resultEndTime": "1954.830s", "languageCode": "en-us"}, {"alternatives": [{}], "resultEndTime": "1961.390s", "languageCode": "en-us"}, {"alternatives": [{}], "resultEndTime": "1963.880s", "languageCode": "en-us"}, {"alternatives": [{}], "resultEndTime": "1965.980s", "languageCode": "en-us"}, {"alternatives": [{}], "resultEndTime": "1973.520s", "languageCode": "en-us"}, {"alternatives": [{}], "resultEndTime": "1976.880s", "languageCode": "en-us"}, {"alternatives": [{}], "resultEndTime": "1983.150s", "languageCode": "en-us"}, {"alternatives": [{}], "resultEndTime": "1986.820s", "languageCode": "en-us"}, {"alternatives": [{}], "resultEndTime": "1993.900s", "languageCode": "en-us"}, {"alternatives": [{}], "resultEndTime": "1999.560s", "languageCode": "en-us"}, {"alternatives": [{}], "resultEndTime": "2006.790s", "languageCode": "en-us"}, {"alternatives": [{}], "resultEndTime": "2008.730s", "languageCode": "en-us"}, {"alternatives": [{}], "resultEndTime": "2014.270s", "languageCode": "en-us"}, {"alternatives": [{}], "resultEndTime": "2020.840s", "languageCode": "en-us"}, {"alternatives": [{}], "resultEndTime": "2023.570s", "languageCode": "en-us"}, {"alternatives": [{}], "resultEndTime": "2024.980s", "languageCode": "en-us"}, {"alternatives": [{}], "resultEndTime": "2030.220s", "languageCode": "en-us"}, {"alternatives": [{}], "resultEndTime": "2034.120s", "languageCode": "en-us"}, {"alternatives": [{}], "resultEndTime": "2037.800s", "languageCode": "en-us"}, {"alternatives": [{}], "resultEndTime": "2039.790s", "languageCode": "en-us"}, {"alternatives": [{}], "resultEndTime": "2048.130s", "languageCode": "en-us"}, {"alternatives": [{}], "resultEndTime": "2048.790s", "languageCode": "en-us"}, {"alternatives": [{}], "resultEndTime": "2058.090s", "languageCode": "en-us"}, {"alternatives": [{}], "resultEndTime": "2070.020s", "languageCode": "en-us"}, {"alternatives": [{}], "resultEndTime": "2072.560s", "languageCode": "en-us"}, {"alternatives": [{}], "resultEndTime": "2078.510s", "languageCode": "en-us"}, {"alternatives": [{}], "resultEndTime": "2082.090s", "languageCode": "en-us"}, {"alternatives": [{}], "resultEndTime": "2086.380s", "languageCode": "en-us"}, {"alternatives": [{}], "resultEndTime": "2092.980s", "languageCode": "en-us"}, {"alternatives": [{}], "resultEndTime": "2096.750s", "languageCode": "en-us"}, {"alternatives": [{}], "resultEndTime": "2105.890s", "languageCode": "en-us"}, {"alternatives": [{}], "resultEndTime": "2107.020s", "languageCode": "en-us"}, {"alternatives": [{}], "resultEndTime": "2113.530s", "languageCode": "en-us"}, {"alternatives": [{}], "resultEndTime": "2121.590s", "languageCode": "en-us"}, {"alternatives": [{}], "resultEndTime": "2132.210s", "languageCode": "en-us"}, {"alternatives": [{}], "resultEndTime": "2134.290s", "languageCode": "en-us"}, {"alternatives": [{}], "resultEndTime": "2135.680s", "languageCode": "en-us"}, {"alternatives": [{}], "resultEndTime": "2137.860s", "languageCode": "en-us"}, {"alternatives": [{}], "resultEndTime": "2142.150s", "languageCode": "en-us"}, {"alternatives": [{}], "resultEndTime": "2144.540s", "languageCode": "en-us"}, {"alternatives": [{}], "resultEndTime": "2146.890s", "languageCode": "en-us"}, {"alternatives": [{}], "resultEndTime": "2148.670s", "languageCode": "en-us"}, {"alternatives": [{}], "resultEndTime": "2152.290s", "languageCode": "en-us"}, {"alternatives": [{}], "resultEndTime": "2155.360s", "languageCode": "en-us"}, {"alternatives": [{}], "resultEndTime": "2161.610s", "languageCode": "en-us"}, {"alternatives": [{}], "resultEndTime": "2165.280s", "languageCode": "en-us"}, {"alternatives": [{}], "resultEndTime": "2168.330s", "languageCode": "en-us"}, {"alternatives": [{}], "resultEndTime": "2172.850s", "languageCode": "en-us"}, {"alternatives": [{}], "resultEndTime": "2178.730s", "languageCode": "en-us"}, {"alternatives": [{}], "resultEndTime": "2182.530s", "languageCode": "en-us"}, {"alternatives": [{}], "resultEndTime": "2194.500s", "languageCode": "en-us"}, {"alternatives": [{}], "resultEndTime": "2195.970s", "languageCode": "en-us"}, {"alternatives": [{}], "resultEndTime": "2202.740s", "languageCode": "en-us"}, {"alternatives": [{}], "resultEndTime": "2208.530s", "languageCode": "en-us"}, {"alternatives": [{}], "resultEndTime": "2214.380s", "languageCode": "en-us"}, {"alternatives": [{}], "resultEndTime": "2217.990s", "languageCode": "en-us"}, {"alternatives": [{}], "resultEndTime": "2220.730s", "languageCode": "en-us"}, {"alternatives": [{}], "resultEndTime": "2225.100s", "languageCode": "en-us"}, {"alternatives": [{}], "resultEndTime": "2227.130s", "languageCode": "en-us"}, {"alternatives": [{}], "resultEndTime": "2228.920s", "languageCode": "en-us"}, {"alternatives": [{}], "resultEndTime": "2231.220s", "languageCode": "en-us"}, {"alternatives": [{}], "resultEndTime": "2236.700s", "languageCode": "en-us"}, {"alternatives": [{}], "resultEndTime": "2241.030s", "languageCode": "en-us"}, {"alternatives": [{}], "resultEndTime": "2244.960s", "languageCode": "en-us"}, {"alternatives": [{}], "resultEndTime": "2251.150s", "languageCode": "en-us"}, {"alternatives": [{}], "resultEndTime": "2256.700s", "languageCode": "en-us"}, {"alternatives": [{}], "resultEndTime": "2259.140s", "languageCode": "en-us"}, {"alternatives": [{}], "resultEndTime": "2264.710s", "languageCode": "en-us"}, {"alternatives": [{}], "resultEndTime": "2265.400s", "languageCode": "en-us"}, {"alternatives": [{}], "resultEndTime": "2268.440s", "languageCode": "en-us"}, {"alternatives": [{}], "resultEndTime": "2269.690s", "languageCode": "en-us"}, {"alternatives": [{}], "resultEndTime": "2272.330s", "languageCode": "en-us"}, {"alternatives": [{}], "resultEndTime": "2273.660s", "languageCode": "en-us"}, {"alternatives": [{}], "resultEndTime": "2277.580s", "languageCode": "en-us"}, {"alternatives": [{}], "resultEndTime": "2278.990s", "languageCode": "en-us"}, {"alternatives": [{}], "resultEndTime": "2280.930s", "languageCode": "en-us"}, {"alternatives": [{}], "resultEndTime": "2284.610s", "languageCode": "en-us"}, {"alternatives": [{}], "resultEndTime": "2291.020s", "languageCode": "en-us"}, {"alternatives": [{}], "resultEndTime": "2294.850s", "languageCode": "en-us"}, {"alternatives": [{}], "resultEndTime": "2298.090s", "languageCode": "en-us"}, {"alternatives": [{}], "resultEndTime": "2302.150s", "languageCode": "en-us"}, {"alternatives": [{}], "resultEndTime": "2305.690s", "languageCode": "en-us"}, {"alternatives": [{}], "resultEndTime": "2310.820s", "languageCode": "en-us"}, {"alternatives": [{}], "resultEndTime": "2313.640s", "languageCode": "en-us"}, {"alternatives": [{}], "resultEndTime": "2322.430s", "languageCode": "en-us"}, {"alternatives": [{}], "resultEndTime": "2328.590s", "languageCode": "en-us"}, {"alternatives": [{}], "resultEndTime": "2331.910s", "languageCode": "en-us"}, {"alternatives": [{}], "resultEndTime": "2337.370s", "languageCode": "en-us"}, {"alternatives": [{}], "resultEndTime": "2338.060s", "languageCode": "en-us"}, {"alternatives": [{}], "resultEndTime": "2340.780s", "languageCode": "en-us"}, {"alternatives": [{}], "resultEndTime": "2344.520s", "languageCode": "en-us"}, {"alternatives": [{}], "resultEndTime": "2346.290s", "languageCode": "en-us"}, {"alternatives": [{}], "resultEndTime": "2348.150s", "languageCode": "en-us"}, {"alternatives": [{}], "resultEndTime": "2351.130s", "languageCode": "en-us"}, {"alternatives": [{}], "resultEndTime": "2355.970s", "languageCode": "en-us"}, {"alternatives": [{}], "resultEndTime": "2357.710s", "languageCode": "en-us"}, {"alternatives": [{}], "resultEndTime": "2359.100s", "languageCode": "en-us"}, {"alternatives": [{}], "resultEndTime": "2362.910s", "languageCode": "en-us"}, {"alternatives": [{}], "resultEndTime": "2365.670s", "languageCode": "en-us"}, {"alternatives": [{}], "resultEndTime": "2368.310s", "languageCode": "en-us"}, {"alternatives": [{}], "resultEndTime": "2376.570s", "languageCode": "en-us"}, {"alternatives": [{}], "resultEndTime": "2379.370s", "languageCode": "en-us"}, {"alternatives": [{}], "resultEndTime": "2383.430s", "languageCode": "en-us"}, {"alternatives": [{}], "resultEndTime": "2387.470s", "languageCode": "en-us"}, {"alternatives": [{}], "resultEndTime": "2390.030s", "languageCode": "en-us"}, {"alternatives": [{}], "resultEndTime": "2392.080s", "languageCode": "en-us"}, {"alternatives": [{}], "resultEndTime": "2397.760s", "languageCode": "en-us"}, {"alternatives": [{}], "resultEndTime": "2404.410s", "languageCode": "en-us"}, {"alternatives": [{}], "resultEndTime": "2407.650s", "languageCode": "en-us"}, {"alternatives": [{}], "resultEndTime": "2411.550s", "languageCode": "en-us"}, {"alternatives": [{}], "resultEndTime": "2413.930s", "languageCode": "en-us"}, {"alternatives": [{}], "resultEndTime": "2419.830s", "languageCode": "en-us"}, {"alternatives": [{}], "resultEndTime": "2421.280s", "languageCode": "en-us"}, {"alternatives": [{}], "resultEndTime": "2425.500s", "languageCode": "en-us"}, {"alternatives": [{}], "resultEndTime": "2427.390s", "languageCode": "en-us"}, {"alternatives": [{}], "resultEndTime": "2429.250s", "languageCode": "en-us"}, {"alternatives": [{}], "resultEndTime": "2439.800s", "languageCode": "en-us"}, {"alternatives": [{}], "resultEndTime": "2446.840s", "languageCode": "en-us"}, {"alternatives": [{}], "resultEndTime": "2449.290s", "languageCode": "en-us"}, {"alternatives": [{}], "resultEndTime": "2452.070s", "languageCode": "en-us"}, {"alternatives": [{}], "resultEndTime": "2456.550s", "languageCode": "en-us"}, {"alternatives": [{}], "resultEndTime": "2459.170s", "languageCode": "en-us"}, {"alternatives": [{}], "resultEndTime": "2468.360s", "languageCode": "en-us"}, {"alternatives": [{}], "resultEndTime": "2471.740s", "languageCode": "en-us"}, {"alternatives": [{}], "resultEndTime": "2475.440s", "languageCode": "en-us"}, {"alternatives": [{}], "resultEndTime": "2479.300s", "languageCode": "en-us"}, {"alternatives": [{}], "resultEndTime": "2480.020s", "languageCode": "en-us"}, {"alternatives": [{}], "resultEndTime": "2481.710s", "languageCode": "en-us"}, {"alternatives": [{}], "resultEndTime": "2485.390s", "languageCode": "en-us"}, {"alternatives": [{}], "resultEndTime": "2489.190s", "languageCode": "en-us"}, {"alternatives": [{}], "resultEndTime": "2492.820s", "languageCode": "en-us"}, {"alternatives": [{}], "resultEndTime": "2495.210s", "languageCode": "en-us"}, {"alternatives": [{}], "resultEndTime": "2500.990s", "languageCode": "en-us"}, {"alternatives": [{}], "resultEndTime": "2503.990s", "languageCode": "en-us"}, {"alternatives": [{}], "resultEndTime": "2514.070s", "languageCode": "en-us"}, {"alternatives": [{}], "resultEndTime": "2520.620s", "languageCode": "en-us"}, {"alternatives": [{}], "resultEndTime": "2524.330s", "languageCode": "en-us"}, {"alternatives": [{}], "resultEndTime": "2527.990s", "languageCode": "en-us"}, {"alternatives": [{}], "resultEndTime": "2531.440s", "languageCode": "en-us"}, {"alternatives": [{}], "resultEndTime": "2537.170s", "languageCode": "en-us"}, {"alternatives": [{}], "resultEndTime": "2538.410s", "languageCode": "en-us"}, {"alternatives": [{}], "resultEndTime": "2540.840s", "languageCode": "en-us"}, {"alternatives": [{}], "resultEndTime": "2543.300s", "languageCode": "en-us"}, {"alternatives": [{}], "resultEndTime": "2546.410s", "languageCode": "en-us"}, {"alternatives": [{}], "resultEndTime": "2553.610s", "languageCode": "en-us"}, {"alternatives": [{}], "resultEndTime": "2555.320s", "languageCode": "en-us"}, {"alternatives": [{}], "resultEndTime": "2562.160s", "languageCode": "en-us"}, {"alternatives": [{}], "resultEndTime": "2564.190s", "languageCode": "en-us"}, {"alternatives": [{}], "resultEndTime": "2566.590s", "languageCode": "en-us"}, {"alternatives": [{}], "resultEndTime": "2572.250s", "languageCode": "en-us"}, {"alternatives": [{}], "resultEndTime": "2573.300s", "languageCode": "en-us"}, {"alternatives": [{}], "resultEndTime": "2575.340s", "languageCode": "en-us"}, {"alternatives": [{}], "resultEndTime": "2579.400s", "languageCode": "en-us"}, {"alternatives": [{}], "resultEndTime": "2584.460s", "languageCode": "en-us"}, {"alternatives": [{}], "resultEndTime": "2588.410s", "languageCode": "en-us"}, {"alternatives": [{}], "resultEndTime": "2603.820s", "languageCode": "en-us"}, {"alternatives": [{}], "resultEndTime": "2606.020s", "languageCode": "en-us"}, {"alternatives": [{}], "resultEndTime": "2607.440s", "languageCode": "en-us"}, {"alternatives": [{}], "resultEndTime": "2611.230s", "languageCode": "en-us"}, {"alternatives": [{}], "resultEndTime": "2616.040s", "languageCode": "en-us"}, {"alternatives": [{}], "resultEndTime": "2618.840s", "languageCode": "en-us"}, {"alternatives": [{}], "resultEndTime": "2624.490s", "languageCode": "en-us"}, {"alternatives": [{}], "resultEndTime": "2626.410s", "languageCode": "en-us"}, {"alternatives": [{}], "resultEndTime": "2632.060s", "languageCode": "en-us"}, {"alternatives": [{}], "resultEndTime": "2633.810s", "languageCode": "en-us"}, {"alternatives": [{}], "resultEndTime": "2637.170s", "languageCode": "en-us"}, {"alternatives": [{}], "resultEndTime": "2638.820s", "languageCode": "en-us"}, {"alternatives": [{}], "resultEndTime": "2641.250s", "languageCode": "en-us"}, {"alternatives": [{}], "resultEndTime": "2645.660s", "languageCode": "en-us"}, {"alternatives": [{}], "resultEndTime": "2647.400s", "languageCode": "en-us"}, {"alternatives": [{}], "resultEndTime": "2651.970s", "languageCode": "en-us"}, {"alternatives": [{}], "resultEndTime": "2654.480s", "languageCode": "en-us"}, {"alternatives": [{}], "resultEndTime": "2656.560s", "languageCode": "en-us"}, {"alternatives": [{}], "resultEndTime": "2658.150s", "languageCode": "en-us"}, {"alternatives": [{}], "resultEndTime": "2665.090s", "languageCode": "en-us"}, {"alternatives": [{}], "resultEndTime": "2667.270s", "languageCode": "en-us"}, {"alternatives": [{}], "resultEndTime": "2675.400s", "languageCode": "en-us"}, {"alternatives": [{}], "resultEndTime": "2678.050s", "languageCode": "en-us"}, {"alternatives": [{}], "resultEndTime": "2686.340s", "languageCode": "en-us"}, {"alternatives": [{}], "resultEndTime": "2698.590s", "languageCode": "en-us"}, {"alternatives": [{}], "resultEndTime": "2700.480s", "languageCode": "en-us"}, {"alternatives": [{}], "resultEndTime": "2704.980s", "languageCode": "en-us"}, {"alternatives": [{}], "resultEndTime": "2707.790s", "languageCode": "en-us"}, {"alternatives": [{}], "resultEndTime": "2711.990s", "languageCode": "en-us"}, {"alternatives": [{}], "resultEndTime": "2713.730s", "languageCode": "en-us"}, {"alternatives": [{}], "resultEndTime": "2715.710s", "languageCode": "en-us"}, {"alternatives": [{}], "resultEndTime": "2717.400s", "languageCode": "en-us"}, {"alternatives": [{}], "resultEndTime": "2725.710s", "languageCode": "en-us"}, {"alternatives": [{}], "resultEndTime": "2728.100s", "languageCode": "en-us"}, {"alternatives": [{}], "resultEndTime": "2730.460s", "languageCode": "en-us"}, {"alternatives": [{}], "resultEndTime": "2733.430s", "languageCode": "en-us"}, {"alternatives": [{}], "resultEndTime": "2736.340s", "languageCode": "en-us"}, {"alternatives": [{}], "resultEndTime": "2741.860s", "languageCode": "en-us"}, {"alternatives": [{}], "resultEndTime": "2746.020s", "languageCode": "en-us"}, {"alternatives": [{}], "resultEndTime": "2750.240s", "languageCode": "en-us"}, {"alternatives": [{}], "resultEndTime": "2752.820s", "languageCode": "en-us"}, {"alternatives": [{}], "resultEndTime": "2755.850s", "languageCode": "en-us"}, {"alternatives": [{}], "resultEndTime": "2760.410s", "languageCode": "en-us"}, {"alternatives": [{}], "resultEndTime": "2764.450s", "languageCode": "en-us"}, {"alternatives": [{}], "resultEndTime": "2767.060s", "languageCode": "en-us"}, {"alternatives": [{}], "resultEndTime": "2768.850s", "languageCode": "en-us"}, {"alternatives": [{}], "resultEndTime": "2770.440s", "languageCode": "en-us"}, {"alternatives": [{}], "resultEndTime": "2775.490s", "languageCode": "en-us"}, {"alternatives": [{}], "resultEndTime": "2782.200s", "languageCode": "en-us"}, {"alternatives": [{}], "resultEndTime": "2786.710s", "languageCode": "en-us"}, {"alternatives": [{}], "resultEndTime": "2788.240s", "languageCode": "en-us"}, {"alternatives": [{}], "resultEndTime": "2791.100s", "languageCode": "en-us"}, {"alternatives": [{}], "resultEndTime": "2794.490s", "languageCode": "en-us"}, {"alternatives": [{}], "resultEndTime": "2797.040s", "languageCode": "en-us"}, {"alternatives": [{}], "resultEndTime": "2801.240s", "languageCode": "en-us"}, {"alternatives": [{}], "resultEndTime": "2806.530s", "languageCode": "en-us"}, {"alternatives": [{}], "resultEndTime": "2810.830s", "languageCode": "en-us"}, {"alternatives": [{}], "resultEndTime": "2814.100s", "languageCode": "en-us"}, {"alternatives": [{}], "resultEndTime": "2815.840s", "languageCode": "en-us"}, {"alternatives": [{}], "resultEndTime": "2819.220s", "languageCode": "en-us"}, {"alternatives": [{}], "resultEndTime": "2820.920s", "languageCode": "en-us"}, {"alternatives": [{}], "resultEndTime": "2823.840s", "languageCode": "en-us"}, {"alternatives": [{}], "resultEndTime": "2828.980s", "languageCode": "en-us"}, {"alternatives": [{}], "resultEndTime": "2830.480s", "languageCode": "en-us"}, {"alternatives": [{}], "resultEndTime": "2834.050s", "languageCode": "en-us"}, {"alternatives": [{}], "resultEndTime": "2839.780s", "languageCode": "en-us"}, {"alternatives": [{}], "resultEndTime": "2844.550s", "languageCode": "en-us"}, {"alternatives": [{}], "resultEndTime": "2846.980s", "languageCode": "en-us"}, {"alternatives": [{}], "resultEndTime": "2851.560s", "languageCode": "en-us"}, {"alternatives": [{}], "resultEndTime": "2856.350s", "languageCode": "en-us"}, {"alternatives": [{}], "resultEndTime": "2858.310s", "languageCode": "en-us"}, {"alternatives": [{}], "resultEndTime": "2864.420s", "languageCode": "en-us"}, {"alternatives": [{}], "resultEndTime": "2866.210s", "languageCode": "en-us"}, {"alternatives": [{}], "resultEndTime": "2872.090s", "languageCode": "en-us"}, {"alternatives": [{}], "resultEndTime": "2873.430s", "languageCode": "en-us"}, {"alternatives": [{}], "resultEndTime": "2878.030s", "languageCode": "en-us"}, {"alternatives": [{}], "resultEndTime": "2880.170s", "languageCode": "en-us"}, {"alternatives": [{}], "resultEndTime": "2882.020s", "languageCode": "en-us"}, {"alternatives": [{}], "resultEndTime": "2885.320s", "languageCode": "en-us"}, {"alternatives": [{}], "resultEndTime": "2886.530s", "languageCode": "en-us"}, {"alternatives": [{}], "resultEndTime": "2891.630s", "languageCode": "en-us"}, {"alternatives": [{}], "resultEndTime": "2894.310s", "languageCode": "en-us"}, {"alternatives": [{}], "resultEndTime": "2900.840s", "languageCode": "en-us"}, {"alternatives": [{}], "resultEndTime": "2903.390s", "languageCode": "en-us"}, {"alternatives": [{}], "resultEndTime": "2907.730s", "languageCode": "en-us"}, {"alternatives": [{}], "resultEndTime": "2910.390s", "languageCode": "en-us"}, {"alternatives": [{}], "resultEndTime": "2914.500s", "languageCode": "en-us"}, {"alternatives": [{}], "resultEndTime": "2915.780s", "languageCode": "en-us"}, {"alternatives": [{}], "resultEndTime": "2919.440s", "languageCode": "en-us"}, {"alternatives": [{}], "resultEndTime": "2921.250s", "languageCode": "en-us"}, {"alternatives": [{}], "resultEndTime": "2925.130s", "languageCode": "en-us"}, {"alternatives": [{}], "resultEndTime": "2928.180s", "languageCode": "en-us"}, {"alternatives": [{}], "resultEndTime": "2930.220s", "languageCode": "en-us"}, {"alternatives": [{}], "resultEndTime": "2934.630s", "languageCode": "en-us"}, {"alternatives": [{}], "resultEndTime": "2943.340s", "languageCode": "en-us"}, {"alternatives": [{}], "resultEndTime": "2947.380s", "languageCode": "en-us"}, {"alternatives": [{}], "resultEndTime": "2950.650s", "languageCode": "en-us"}, {"alternatives": [{}], "resultEndTime": "2953.860s", "languageCode": "en-us"}, {"alternatives": [{}], "resultEndTime": "2956.240s", "languageCode": "en-us"}, {"alternatives": [{}], "resultEndTime": "2959.180s", "languageCode": "en-us"}, {"alternatives": [{}], "resultEndTime": "2963.340s", "languageCode": "en-us"}, {"alternatives": [{}], "resultEndTime": "2964.630s", "languageCode": "en-us"}, {"alternatives": [{}], "resultEndTime": "2966.440s", "languageCode": "en-us"}, {"alternatives": [{}], "resultEndTime": "2969.170s", "languageCode": "en-us"}, {"alternatives": [{}], "resultEndTime": "2974.650s", "languageCode": "en-us"}, {"alternatives": [{}], "resultEndTime": "2976.550s", "languageCode": "en-us"}, {"alternatives": [{}], "resultEndTime": "2983.100s", "languageCode": "en-us"}, {"alternatives": [{}], "resultEndTime": "2987.680s", "languageCode": "en-us"}, {"alternatives": [{}], "resultEndTime": "2993.010s", "languageCode": "en-us"}, {"alternatives": [{}], "resultEndTime": "2996.330s", "languageCode": "en-us"}, {"alternatives": [{}], "resultEndTime": "2998.810s", "languageCode": "en-us"}, {"alternatives": [{}], "resultEndTime": "3001.850s", "languageCode": "en-us"}, {"alternatives": [{}], "resultEndTime": "3003.400s", "languageCode": "en-us"}, {"alternatives": [{}], "resultEndTime": "3007.880s", "languageCode": "en-us"}, {"alternatives": [{}], "resultEndTime": "3010.950s", "languageCode": "en-us"}, {"alternatives": [{}], "resultEndTime": "3012.910s", "languageCode": "en-us"}, {"alternatives": [{}], "resultEndTime": "3015.170s", "languageCode": "en-us"}, {"alternatives": [{}], "resultEndTime": "3019.860s", "languageCode": "en-us"}, {"alternatives": [{}], "resultEndTime": "3022.800s", "languageCode": "en-us"}, {"alternatives": [{}], "resultEndTime": "3025.900s", "languageCode": "en-us"}, {"alternatives": [{}], "resultEndTime": "3027.480s", "languageCode": "en-us"}, {"alternatives": [{}], "resultEndTime": "3033.060s", "languageCode": "en-us"}, {"alternatives": [{}], "resultEndTime": "3038.110s", "languageCode": "en-us"}, {"alternatives": [{}], "resultEndTime": "3039.530s", "languageCode": "en-us"}, {"alternatives": [{}], "resultEndTime": "3041.680s", "languageCode": "en-us"}, {"alternatives": [{}], "resultEndTime": "3043.290s", "languageCode": "en-us"}, {"alternatives": [{}], "resultEndTime": "3045.180s", "languageCode": "en-us"}, {"alternatives": [{}], "resultEndTime": "3049.900s", "languageCode": "en-us"}, {"alternatives": [{}], "resultEndTime": "3052.570s", "languageCode": "en-us"}, {"alternatives": [{}], "resultEndTime": "3054.250s", "languageCode": "en-us"}, {"alternatives": [{}], "resultEndTime": "3055.570s", "languageCode": "en-us"}, {"alternatives": [{}], "resultEndTime": "3058.900s", "languageCode": "en-us"}, {"alternatives": [{}], "resultEndTime": "3065.350s", "languageCode": "en-us"}, {"alternatives": [{}], "resultEndTime": "3069.290s", "languageCode": "en-us"}, {"alternatives": [{}], "resultEndTime": "3072.160s", "languageCode": "en-us"}, {"alternatives": [{}], "resultEndTime": "3075.080s", "languageCode": "en-us"}, {"alternatives": [{}], "resultEndTime": "3082.210s", "languageCode": "en-us"}, {"alternatives": [{}], "resultEndTime": "3083.800s", "languageCode": "en-us"}, {"alternatives": [{}], "resultEndTime": "3087.650s", "languageCode": "en-us"}, {"alternatives": [{}], "resultEndTime": "3091.650s", "languageCode": "en-us"}, {"alternatives": [{}], "resultEndTime": "3096.510s", "languageCode": "en-us"}, {"alternatives": [{}], "resultEndTime": "3106.040s", "languageCode": "en-us"}, {"alternatives": [{}], "resultEndTime": "3110.020s", "languageCode": "en-us"}, {"alternatives": [{}], "resultEndTime": "3115.940s", "languageCode": "en-us"}, {"alternatives": [{}], "resultEndTime": "3123.520s", "languageCode": "en-us"}, {"alternatives": [{}], "resultEndTime": "3127.040s", "languageCode": "en-us"}, {"alternatives": [{}], "resultEndTime": "3129.760s", "languageCode": "en-us"}, {"alternatives": [{}], "resultEndTime": "3134.190s", "languageCode": "en-us"}, {"alternatives": [{}], "resultEndTime": "3137.580s", "languageCode": "en-us"}, {"alternatives": [{}], "resultEndTime": "3139.720s", "languageCode": "en-us"}, {"alternatives": [{}], "resultEndTime": "3141.480s", "languageCode": "en-us"}, {"alternatives": [{}], "resultEndTime": "3148.780s", "languageCode": "en-us"}, {"alternatives": [{}], "resultEndTime": "3150.820s", "languageCode": "en-us"}, {"alternatives": [{}], "resultEndTime": "3154.980s", "languageCode": "en-us"}, {"alternatives": [{}], "resultEndTime": "3157.960s", "languageCode": "en-us"}, {"alternatives": [{}], "resultEndTime": "3159.460s", "languageCode": "en-us"}, {"alternatives": [{}], "resultEndTime": "3161.690s", "languageCode": "en-us"}, {"alternatives": [{}], "resultEndTime": "3163.810s", "languageCode": "en-us"}, {"alternatives": [{}], "resultEndTime": "3170.380s", "languageCode": "en-us"}, {"alternatives": [{}], "resultEndTime": "3173.380s", "languageCode": "en-us"}, {"alternatives": [{}], "resultEndTime": "3175.820s", "languageCode": "en-us"}, {"alternatives": [{}], "resultEndTime": "3177.970s", "languageCode": "en-us"}, {"alternatives": [{}], "resultEndTime": "3184.400s", "languageCode": "en-us"}, {"alternatives": [{}], "resultEndTime": "3190.480s", "languageCode": "en-us"}, {"alternatives": [{}], "resultEndTime": "3197.030s", "languageCode": "en-us"}, {"alternatives": [{}], "resultEndTime": "3200.290s", "languageCode": "en-us"}, {"alternatives": [{}], "resultEndTime": "3201.010s", "languageCode": "en-us"}, {"alternatives": [{}], "resultEndTime": "3203.900s", "languageCode": "en-us"}, {"alternatives": [{}], "resultEndTime": "3206.280s", "languageCode": "en-us"}, {"alternatives": [{}], "resultEndTime": "3209.520s", "languageCode": "en-us"}, {"alternatives": [{}], "resultEndTime": "3211.130s", "languageCode": "en-us"}, {"alternatives": [{}], "resultEndTime": "3217.450s", "languageCode": "en-us"}, {"alternatives": [{}], "resultEndTime": "3220.840s", "languageCode": "en-us"}, {"alternatives": [{}], "resultEndTime": "3225.100s", "languageCode": "en-us"}, {"alternatives": [{}], "resultEndTime": "3227.490s", "languageCode": "en-us"}, {"alternatives": [{}], "resultEndTime": "3230.520s", "languageCode": "en-us"}, {"alternatives": [{}], "resultEndTime": "3233.550s", "languageCode": "en-us"}, {"alternatives": [{}], "resultEndTime": "3238.860s", "languageCode": "en-us"}, {"alternatives": [{}], "resultEndTime": "3242.690s", "languageCode": "en-us"}, {"alternatives": [{}], "resultEndTime": "3245.300s", "languageCode": "en-us"}, {"alternatives": [{}], "resultEndTime": "3246.940s", "languageCode": "en-us"}, {"alternatives": [{}], "resultEndTime": "3249.090s", "languageCode": "en-us"}, {"alternatives": [{}], "resultEndTime": "3251.040s", "languageCode": "en-us"}, {"alternatives": [{}], "resultEndTime": "3255.430s", "languageCode": "en-us"}, {"alternatives": [{}], "resultEndTime": "3256.930s", "languageCode": "en-us"}, {"alternatives": [{}], "resultEndTime": "3260.970s", "languageCode": "en-us"}, {"alternatives": [{}], "resultEndTime": "3264.460s", "languageCode": "en-us"}, {"alternatives": [{}], "resultEndTime": "3266.970s", "languageCode": "en-us"}, {"alternatives": [{}], "resultEndTime": "3268.740s", "languageCode": "en-us"}, {"alternatives": [{}], "resultEndTime": "3271.530s", "languageCode": "en-us"}, {"alternatives": [{}], "resultEndTime": "3272.280s", "languageCode": "en-us"}, {"alternatives": [{}], "resultEndTime": "3274.580s", "languageCode": "en-us"}, {"alternatives": [{}], "resultEndTime": "3278.690s", "languageCode": "en-us"}, {"alternatives": [{}], "resultEndTime": "3281.840s", "languageCode": "en-us"}, {"alternatives": [{}], "resultEndTime": "3284.700s", "languageCode": "en-us"}, {"alternatives": [{}], "resultEndTime": "3286.170s", "languageCode": "en-us"}, {"alternatives": [{}], "resultEndTime": "3289.060s", "languageCode": "en-us"}, {"alternatives": [{}], "resultEndTime": "3290.700s", "languageCode": "en-us"}, {"alternatives": [{}], "resultEndTime": "3297.910s", "languageCode": "en-us"}, {"alternatives": [{}], "resultEndTime": "3300.480s", "languageCode": "en-us"}, {"alternatives": [{}], "resultEndTime": "3304.310s", "languageCode": "en-us"}, {"alternatives": [{}], "resultEndTime": "3309.440s", "languageCode": "en-us"}, {"alternatives": [{}], "resultEndTime": "3311.360s", "languageCode": "en-us"}, {"alternatives": [{}], "resultEndTime": "3314.490s", "languageCode": "en-us"}, {"alternatives": [{}], "resultEndTime": "3317.970s", "languageCode": "en-us"}, {"alternatives": [{}], "resultEndTime": "3321.920s", "languageCode": "en-us"}, {"alternatives": [{}], "resultEndTime": "3325.090s", "languageCode": "en-us"}, {"alternatives": [{}], "resultEndTime": "3328.990s", "languageCode": "en-us"}, {"alternatives": [{}], "resultEndTime": "3332.430s", "languageCode": "en-us"}, {"alternatives": [{}], "resultEndTime": "3335.070s", "languageCode": "en-us"}, {"alternatives": [{}], "resultEndTime": "3337.280s", "languageCode": "en-us"}, {"alternatives": [{}], "resultEndTime": "3343.410s", "languageCode": "en-us"}, {"alternatives": [{}], "resultEndTime": "3344.010s", "languageCode": "en-us"}, {"alternatives": [{}], "resultEndTime": "3348.290s", "languageCode": "en-us"}, {"alternatives": [{}], "resultEndTime": "3354.430s", "languageCode": "en-us"}, {"alternatives": [{}], "resultEndTime": "3358.170s", "languageCode": "en-us"}, {"alternatives": [{}], "resultEndTime": "3360.580s", "languageCode": "en-us"}, {"alternatives": [{}], "resultEndTime": "3364.560s", "languageCode": "en-us"}, {"alternatives": [{}], "resultEndTime": "3365.940s", "languageCode": "en-us"}, {"alternatives": [{}], "resultEndTime": "3368.350s", "languageCode": "en-us"}, {"alternatives": [{}], "resultEndTime": "3372.530s", "languageCode": "en-us"}, {"alternatives": [{}], "resultEndTime": "3374.530s", "languageCode": "en-us"}, {"alternatives": [{}], "resultEndTime": "3378.270s", "languageCode": "en-us"}, {"alternatives": [{}], "resultEndTime": "3380.140s", "languageCode": "en-us"}, {"alternatives": [{}], "resultEndTime": "3392.110s", "languageCode": "en-us"}, {"alternatives": [{}], "resultEndTime": "3393.840s", "languageCode": "en-us"}, {"alternatives": [{}], "resultEndTime": "3404.140s", "languageCode": "en-us"}, {"alternatives": [{}], "resultEndTime": "3412.590s", "languageCode": "en-us"}, {"alternatives": [{}], "resultEndTime": "3416.170s", "languageCode": "en-us"}, {"alternatives": [{}], "resultEndTime": "3416.920s", "languageCode": "en-us"}, {"alternatives": [{}], "resultEndTime": "3419.020s", "languageCode": "en-us"}, {"alternatives": [{}], "resultEndTime": "3426.300s", "languageCode": "en-us"}, {"alternatives": [{}], "resultEndTime": "3428.920s", "languageCode": "en-us"}, {"alternatives": [{}], "resultEndTime": "3435.510s", "languageCode": "en-us"}, {"alternatives": [{}], "resultEndTime": "3440.930s", "languageCode": "en-us"}, {"alternatives": [{}], "resultEndTime": "3452.910s", "languageCode": "en-us"}, {"alternatives": [{}], "resultEndTime": "3464.930s", "languageCode": "en-us"}, {"alternatives": [{}], "resultEndTime": "3476.930s", "languageCode": "en-us"}, {"alternatives": [{}], "resultEndTime": "3488.930s", "languageCode": "en-us"}, {"alternatives": [{}], "resultEndTime": "3489.680s", "languageCode": "en-us"}, {"alternatives": [{}], "resultEndTime": "3501.660s", "languageCode": "en-us"}, {"alternatives": [{}], "resultEndTime": "3513.670s", "languageCode": "en-us"}, {"alternatives": [{}], "resultEndTime": "3525.630s", "languageCode": "en-us"}, {"alternatives": [{}], "resultEndTime": "3537.690s", "languageCode": "en-us"}, {"alternatives": [{}], "resultEndTime": "3549.650s", "languageCode": "en-us"}, {"alternatives": [{}], "resultEndTime": "3561.650s", "languageCode": "en-us"}, {"alternatives": [{}], "resultEndTime": "3562.430s", "languageCode": "en-us"}, {"alternatives": [{}], "resultEndTime": "3574.380s", "languageCode": "en-us"}, {"alternatives": [{}], "resultEndTime": "3586.430s", "languageCode": "en-us"}, {"alternatives": [{}], "resultEndTime": "3598.380s", "languageCode": "en-us"}, {"alternatives": [{}], "resultEndTime": "3610.370s", "languageCode": "en-us"}, {"alternatives": [{}], "resultEndTime": "3622.430s", "languageCode": "en-us"}], "totalBilledTime": "3623s"}