{"results": [{"alternatives": [{}], "resultEndTime": "4.310s", "languageCode": "en-us"}, {"alternatives": [{"transcript": "good morning I would like to take a minute or two to discuss a subject that is vitally important to all of us I'm talking of course about the annual free gift that we send to every TSM", "confidence": 0.9128384, "words": [{"startTime": "11.800s", "endTime": "12s", "word": "good"}, {"startTime": "12s", "endTime": "12.500s", "word": "morning"}, {"startTime": "13.700s", "endTime": "13.800s", "word": "I"}, {"startTime": "13.800s", "endTime": "13.900s", "word": "would"}, {"startTime": "13.900s", "endTime": "14.100s", "word": "like"}, {"startTime": "14.100s", "endTime": "14.200s", "word": "to"}, {"startTime": "14.200s", "endTime": "14.500s", "word": "take"}, {"startTime": "14.500s", "endTime": "14.500s", "word": "a"}, {"startTime": "14.500s", "endTime": "14.900s", "word": "minute"}, {"startTime": "14.900s", "endTime": "15s", "word": "or"}, {"startTime": "15s", "endTime": "15.500s", "word": "two"}, {"startTime": "15.800s", "endTime": "15.900s", "word": "to"}, {"startTime": "15.900s", "endTime": "16.400s", "word": "discuss"}, {"startTime": "16.400s", "endTime": "16.400s", "word": "a"}, {"startTime": "16.400s", "endTime": "17.200s", "word": "subject"}, {"startTime": "17.200s", "endTime": "17.400s", "word": "that"}, {"startTime": "17.400s", "endTime": "17.500s", "word": "is"}, {"startTime": "17.500s", "endTime": "18s", "word": "vitally"}, {"startTime": "18s", "endTime": "18.800s", "word": "important"}, {"startTime": "18.800s", "endTime": "18.900s", "word": "to"}, {"startTime": "18.900s", "endTime": "19.100s", "word": "all"}, {"startTime": "19.100s", "endTime": "19.200s", "word": "of"}, {"startTime": "19.200s", "endTime": "19.600s", "word": "us"}, {"startTime": "20.700s", "endTime": "20.800s", "word": "I'm"}, {"startTime": "20.800s", "endTime": "21.200s", "word": "talking"}, {"startTime": "21.200s", "endTime": "21.300s", "word": "of"}, {"startTime": "21.300s", "endTime": "21.900s", "word": "course"}, {"startTime": "22.200s", "endTime": "22.500s", "word": "about"}, {"startTime": "22.500s", "endTime": "22.700s", "word": "the"}, {"startTime": "22.700s", "endTime": "23.200s", "word": "annual"}, {"startTime": "23.200s", "endTime": "23.400s", "word": "free"}, {"startTime": "23.400s", "endTime": "24.100s", "word": "gift"}, {"startTime": "24.100s", "endTime": "24.300s", "word": "that"}, {"startTime": "24.300s", "endTime": "24.400s", "word": "we"}, {"startTime": "24.400s", "endTime": "24.800s", "word": "send"}, {"startTime": "24.800s", "endTime": "25s", "word": "to"}, {"startTime": "25s", "endTime": "25.400s", "word": "every"}, {"startTime": "25.400s", "endTime": "26.200s", "word": "TSM"}]}], "resultEndTime": "26.610s", "languageCode": "en-us"}, {"alternatives": [{"transcript": " your basic ball and your basic bat or a big hit with the field sales force", "confidence": 0.89325666, "words": [{"startTime": "27.300s", "endTime": "27.500s", "word": "your"}, {"startTime": "27.500s", "endTime": "27.900s", "word": "basic"}, {"startTime": "27.900s", "endTime": "28.600s", "word": "ball"}, {"startTime": "28.700s", "endTime": "28.900s", "word": "and"}, {"startTime": "28.900s", "endTime": "29s", "word": "your"}, {"startTime": "29s", "endTime": "29.400s", "word": "basic"}, {"startTime": "29.400s", "endTime": "30s", "word": "bat"}, {"startTime": "30.200s", "endTime": "30.400s", "word": "or"}, {"startTime": "30.400s", "endTime": "30.400s", "word": "a"}, {"startTime": "30.400s", "endTime": "30.800s", "word": "big"}, {"startTime": "30.800s", "endTime": "31.200s", "word": "hit"}, {"startTime": "31.200s", "endTime": "31.300s", "word": "with"}, {"startTime": "31.300s", "endTime": "31.400s", "word": "the"}, {"startTime": "31.400s", "endTime": "31.700s", "word": "field"}, {"startTime": "31.700s", "endTime": "32.100s", "word": "sales"}, {"startTime": "32.100s", "endTime": "32.600s", "word": "force"}]}], "resultEndTime": "33.980s", "languageCode": "en-us"}, {"alternatives": [{"transcript": " and the question that's been keeping us up nights here in New York City is how do we top that", "confidence": 0.86642915, "words": [{"startTime": "35.100s", "endTime": "35.200s", "word": "and"}, {"startTime": "35.200s", "endTime": "35.300s", "word": "the"}, {"startTime": "35.300s", "endTime": "35.800s", "word": "question"}, {"startTime": "35.800s", "endTime": "36s", "word": "that's"}, {"startTime": "36s", "endTime": "36.100s", "word": "been"}, {"startTime": "36.100s", "endTime": "36.500s", "word": "keeping"}, {"startTime": "36.500s", "endTime": "36.600s", "word": "us"}, {"startTime": "36.600s", "endTime": "36.900s", "word": "up"}, {"startTime": "36.900s", "endTime": "37.500s", "word": "nights"}, {"startTime": "37.800s", "endTime": "38s", "word": "here"}, {"startTime": "38s", "endTime": "38s", "word": "in"}, {"startTime": "38s", "endTime": "38.200s", "word": "New"}, {"startTime": "38.200s", "endTime": "38.400s", "word": "York"}, {"startTime": "38.400s", "endTime": "38.800s", "word": "City"}, {"startTime": "39.500s", "endTime": "39.700s", "word": "is"}, {"startTime": "39.700s", "endTime": "39.900s", "word": "how"}, {"startTime": "39.900s", "endTime": "40s", "word": "do"}, {"startTime": "40s", "endTime": "40.100s", "word": "we"}, {"startTime": "40.100s", "endTime": "40.500s", "word": "top"}, {"startTime": "40.500s", "endTime": "40.900s", "word": "that"}]}], "resultEndTime": "41.390s", "languageCode": "en-us"}, {"alternatives": [{"transcript": " basic boxing gloves no research showed that it's difficult to put up POS materials with these fat thumbs", "confidence": 0.9082395, "words": [{"startTime": "42.400s", "endTime": "42.800s", "word": "basic"}, {"startTime": "42.800s", "endTime": "43.100s", "word": "boxing"}, {"startTime": "43.100s", "endTime": "43.700s", "word": "gloves"}, {"startTime": "44.500s", "endTime": "45.100s", "word": "no"}, {"startTime": "45.500s", "endTime": "46.100s", "word": "research"}, {"startTime": "46.100s", "endTime": "46.600s", "word": "showed"}, {"startTime": "46.600s", "endTime": "46.700s", "word": "that"}, {"startTime": "46.700s", "endTime": "46.900s", "word": "it's"}, {"startTime": "46.900s", "endTime": "47.500s", "word": "difficult"}, {"startTime": "47.500s", "endTime": "47.600s", "word": "to"}, {"startTime": "47.600s", "endTime": "47.800s", "word": "put"}, {"startTime": "47.800s", "endTime": "47.900s", "word": "up"}, {"startTime": "47.900s", "endTime": "48.400s", "word": "POS"}, {"startTime": "48.400s", "endTime": "49.100s", "word": "materials"}, {"startTime": "49.200s", "endTime": "49.400s", "word": "with"}, {"startTime": "49.400s", "endTime": "49.700s", "word": "these"}, {"startTime": "49.700s", "endTime": "50s", "word": "fat"}, {"startTime": "50s", "endTime": "50.600s", "word": "thumbs"}]}], "resultEndTime": "51.230s", "languageCode": "en-us"}, {"alternatives": [{"transcript": " your basic hard hat it could come in handy when those competitive shears come crashing down but we decided against it", "confidence": 0.867884, "words": [{"startTime": "52.900s", "endTime": "53.100s", "word": "your"}, {"startTime": "53.100s", "endTime": "53.500s", "word": "basic"}, {"startTime": "53.500s", "endTime": "53.800s", "word": "hard"}, {"startTime": "53.800s", "endTime": "54.300s", "word": "hat"}, {"startTime": "54.900s", "endTime": "55s", "word": "it"}, {"startTime": "55s", "endTime": "55.200s", "word": "could"}, {"startTime": "55.200s", "endTime": "55.400s", "word": "come"}, {"startTime": "55.400s", "endTime": "55.500s", "word": "in"}, {"startTime": "55.500s", "endTime": "56.100s", "word": "handy"}, {"startTime": "56.400s", "endTime": "56.500s", "word": "when"}, {"startTime": "56.500s", "endTime": "56.700s", "word": "those"}, {"startTime": "56.700s", "endTime": "57.300s", "word": "competitive"}, {"startTime": "57.300s", "endTime": "57.700s", "word": "shears"}, {"startTime": "57.700s", "endTime": "57.900s", "word": "come"}, {"startTime": "57.900s", "endTime": "58.300s", "word": "crashing"}, {"startTime": "58.300s", "endTime": "58.800s", "word": "down"}, {"startTime": "59.400s", "endTime": "59.900s", "word": "but"}, {"startTime": "60.400s", "endTime": "60.500s", "word": "we"}, {"startTime": "60.500s", "endTime": "61.100s", "word": "decided"}, {"startTime": "61.100s", "endTime": "61.500s", "word": "against"}, {"startTime": "61.500s", "endTime": "61.900s", "word": "it"}]}], "resultEndTime": "62.380s", "languageCode": "en-us"}, {"alternatives": [{"transcript": " this year we wanted to give you something you could really use and that's why we decided on this watch later on you'll each be getting one of these why because basic and good timing or the subjects of this meeting", "confidence": 0.91283834, "words": [{"startTime": "63.500s", "endTime": "63.800s", "word": "this"}, {"startTime": "63.800s", "endTime": "64.200s", "word": "year"}, {"startTime": "64.300s", "endTime": "64.500s", "word": "we"}, {"startTime": "64.500s", "endTime": "64.800s", "word": "wanted"}, {"startTime": "64.800s", "endTime": "64.900s", "word": "to"}, {"startTime": "64.900s", "endTime": "65.200s", "word": "give"}, {"startTime": "65.200s", "endTime": "65.400s", "word": "you"}, {"startTime": "65.400s", "endTime": "66.100s", "word": "something"}, {"startTime": "66.200s", "endTime": "66.300s", "word": "you"}, {"startTime": "66.300s", "endTime": "66.500s", "word": "could"}, {"startTime": "66.500s", "endTime": "66.800s", "word": "really"}, {"startTime": "66.800s", "endTime": "67.300s", "word": "use"}, {"startTime": "68.100s", "endTime": "68.300s", "word": "and"}, {"startTime": "68.300s", "endTime": "68.500s", "word": "that's"}, {"startTime": "68.500s", "endTime": "69s", "word": "why"}, {"startTime": "69s", "endTime": "69.100s", "word": "we"}, {"startTime": "69.100s", "endTime": "69.800s", "word": "decided"}, {"startTime": "69.800s", "endTime": "70s", "word": "on"}, {"startTime": "70s", "endTime": "70.300s", "word": "this"}, {"startTime": "70.300s", "endTime": "70.900s", "word": "watch"}, {"startTime": "71.700s", "endTime": "72.100s", "word": "later"}, {"startTime": "72.100s", "endTime": "72.500s", "word": "on"}, {"startTime": "72.600s", "endTime": "72.800s", "word": "you'll"}, {"startTime": "72.900s", "endTime": "73.200s", "word": "each"}, {"startTime": "73.200s", "endTime": "73.400s", "word": "be"}, {"startTime": "73.400s", "endTime": "73.800s", "word": "getting"}, {"startTime": "73.800s", "endTime": "74s", "word": "one"}, {"startTime": "74s", "endTime": "74.100s", "word": "of"}, {"startTime": "74.100s", "endTime": "74.600s", "word": "these"}, {"startTime": "75.600s", "endTime": "76.100s", "word": "why"}, {"startTime": "76.900s", "endTime": "77.300s", "word": "because"}, {"startTime": "77.300s", "endTime": "78.100s", "word": "basic"}, {"startTime": "78.200s", "endTime": "78.600s", "word": "and"}, {"startTime": "78.600s", "endTime": "78.900s", "word": "good"}, {"startTime": "78.900s", "endTime": "79.400s", "word": "timing"}, {"startTime": "80.300s", "endTime": "80.400s", "word": "or"}, {"startTime": "80.400s", "endTime": "80.600s", "word": "the"}, {"startTime": "80.600s", "endTime": "81.100s", "word": "subjects"}, {"startTime": "81.100s", "endTime": "81.100s", "word": "of"}, {"startTime": "81.100s", "endTime": "81.300s", "word": "this"}, {"startTime": "81.300s", "endTime": "81.800s", "word": "meeting"}]}], "resultEndTime": "82.220s", "languageCode": "en-us"}, {"alternatives": [{"transcript": " before we talk about our present opportunities and our future plans let's revisit the past for a moment", "confidence": 0.91020656, "words": [{"startTime": "83.100s", "endTime": "83.400s", "word": "before"}, {"startTime": "83.400s", "endTime": "83.500s", "word": "we"}, {"startTime": "83.500s", "endTime": "83.800s", "word": "talk"}, {"startTime": "83.800s", "endTime": "84.100s", "word": "about"}, {"startTime": "84.100s", "endTime": "84.200s", "word": "our"}, {"startTime": "84.200s", "endTime": "84.600s", "word": "present"}, {"startTime": "84.600s", "endTime": "85.500s", "word": "opportunities"}, {"startTime": "85.700s", "endTime": "85.800s", "word": "and"}, {"startTime": "85.800s", "endTime": "85.900s", "word": "our"}, {"startTime": "85.900s", "endTime": "86.300s", "word": "future"}, {"startTime": "86.300s", "endTime": "87s", "word": "plans"}, {"startTime": "87.700s", "endTime": "88.300s", "word": "let's"}, {"startTime": "88.600s", "endTime": "89.100s", "word": "revisit"}, {"startTime": "89.100s", "endTime": "89.200s", "word": "the"}, {"startTime": "89.200s", "endTime": "89.600s", "word": "past"}, {"startTime": "89.600s", "endTime": "89.700s", "word": "for"}, {"startTime": "89.700s", "endTime": "89.800s", "word": "a"}, {"startTime": "89.800s", "endTime": "90.400s", "word": "moment"}]}], "resultEndTime": "90.730s", "languageCode": "en-us"}, {"alternatives": [{"transcript": " at the beginning of 1994 we thought basic could live with that instant price Gap in fact we discovered that we could live with a much larger price Gap", "confidence": 0.8481045, "words": [{"startTime": "91.700s", "endTime": "91.900s", "word": "at"}, {"startTime": "91.900s", "endTime": "91.900s", "word": "the"}, {"startTime": "91.900s", "endTime": "92.300s", "word": "beginning"}, {"startTime": "92.300s", "endTime": "92.400s", "word": "of"}, {"startTime": "92.400s", "endTime": "93.700s", "word": "1994"}, {"startTime": "94.500s", "endTime": "94.600s", "word": "we"}, {"startTime": "94.600s", "endTime": "94.900s", "word": "thought"}, {"startTime": "94.900s", "endTime": "95.400s", "word": "basic"}, {"startTime": "95.400s", "endTime": "95.700s", "word": "could"}, {"startTime": "95.700s", "endTime": "96.200s", "word": "live"}, {"startTime": "96.200s", "endTime": "96.300s", "word": "with"}, {"startTime": "96.300s", "endTime": "96.600s", "word": "that"}, {"startTime": "96.600s", "endTime": "97s", "word": "instant"}, {"startTime": "97s", "endTime": "97.400s", "word": "price"}, {"startTime": "97.400s", "endTime": "97.800s", "word": "Gap"}, {"startTime": "98.800s", "endTime": "99s", "word": "in"}, {"startTime": "99s", "endTime": "99.900s", "word": "fact"}, {"startTime": "99.900s", "endTime": "100s", "word": "we"}, {"startTime": "100s", "endTime": "100.800s", "word": "discovered"}, {"startTime": "100.800s", "endTime": "101s", "word": "that"}, {"startTime": "101s", "endTime": "101.100s", "word": "we"}, {"startTime": "101.100s", "endTime": "101.300s", "word": "could"}, {"startTime": "101.300s", "endTime": "101.800s", "word": "live"}, {"startTime": "102s", "endTime": "102.200s", "word": "with"}, {"startTime": "102.200s", "endTime": "102.400s", "word": "a"}, {"startTime": "102.400s", "endTime": "103s", "word": "much"}, {"startTime": "103s", "endTime": "103.700s", "word": "larger"}, {"startTime": "103.800s", "endTime": "104.100s", "word": "price"}, {"startTime": "104.100s", "endTime": "104.600s", "word": "Gap"}]}], "resultEndTime": "104.950s", "languageCode": "en-us"}, {"alternatives": [{"transcript": " that Gap is proof positive that every one of you in the field sales force is doing a great job at executing our strategy", "confidence": 0.8640836, "words": [{"startTime": "105.900s", "endTime": "106.200s", "word": "that"}, {"startTime": "106.200s", "endTime": "106.900s", "word": "Gap"}, {"startTime": "107s", "endTime": "107.200s", "word": "is"}, {"startTime": "107.200s", "endTime": "107.600s", "word": "proof"}, {"startTime": "107.600s", "endTime": "108.400s", "word": "positive"}, {"startTime": "108.700s", "endTime": "109s", "word": "that"}, {"startTime": "109s", "endTime": "109.300s", "word": "every"}, {"startTime": "109.300s", "endTime": "109.400s", "word": "one"}, {"startTime": "109.400s", "endTime": "109.600s", "word": "of"}, {"startTime": "109.600s", "endTime": "110s", "word": "you"}, {"startTime": "110.200s", "endTime": "110.300s", "word": "in"}, {"startTime": "110.300s", "endTime": "110.400s", "word": "the"}, {"startTime": "110.400s", "endTime": "110.700s", "word": "field"}, {"startTime": "110.700s", "endTime": "111.100s", "word": "sales"}, {"startTime": "111.100s", "endTime": "111.600s", "word": "force"}, {"startTime": "112.100s", "endTime": "112.400s", "word": "is"}, {"startTime": "112.400s", "endTime": "112.800s", "word": "doing"}, {"startTime": "112.800s", "endTime": "113s", "word": "a"}, {"startTime": "113s", "endTime": "113.500s", "word": "great"}, {"startTime": "113.500s", "endTime": "114.100s", "word": "job"}, {"startTime": "114.300s", "endTime": "114.500s", "word": "at"}, {"startTime": "114.500s", "endTime": "115.200s", "word": "executing"}, {"startTime": "115.300s", "endTime": "115.500s", "word": "our"}, {"startTime": "115.500s", "endTime": "116.200s", "word": "strategy"}]}], "resultEndTime": "116.640s", "languageCode": "en-us"}, {"alternatives": [{"transcript": " your achievement is even more impressive when you consider the tough challenges we faced in 1995 time and time again in 95 you met those challenges you did more than just Prevail against tough odds you excelled", "confidence": 0.9128384, "words": [{"startTime": "117.500s", "endTime": "117.800s", "word": "your"}, {"startTime": "117.800s", "endTime": "118.400s", "word": "achievement"}, {"startTime": "118.400s", "endTime": "118.600s", "word": "is"}, {"startTime": "118.600s", "endTime": "118.800s", "word": "even"}, {"startTime": "118.800s", "endTime": "119s", "word": "more"}, {"startTime": "119s", "endTime": "119.800s", "word": "impressive"}, {"startTime": "120.100s", "endTime": "120.200s", "word": "when"}, {"startTime": "120.200s", "endTime": "120.400s", "word": "you"}, {"startTime": "120.400s", "endTime": "121s", "word": "consider"}, {"startTime": "121s", "endTime": "121.200s", "word": "the"}, {"startTime": "121.200s", "endTime": "121.500s", "word": "tough"}, {"startTime": "121.500s", "endTime": "122.300s", "word": "challenges"}, {"startTime": "122.500s", "endTime": "122.700s", "word": "we"}, {"startTime": "122.700s", "endTime": "123.200s", "word": "faced"}, {"startTime": "123.200s", "endTime": "123.300s", "word": "in"}, {"startTime": "123.300s", "endTime": "124.700s", "word": "1995"}, {"startTime": "125.700s", "endTime": "126.200s", "word": "time"}, {"startTime": "126.200s", "endTime": "126.400s", "word": "and"}, {"startTime": "126.400s", "endTime": "126.700s", "word": "time"}, {"startTime": "126.700s", "endTime": "127s", "word": "again"}, {"startTime": "127s", "endTime": "127.200s", "word": "in"}, {"startTime": "127.200s", "endTime": "128.100s", "word": "95"}, {"startTime": "128.300s", "endTime": "128.500s", "word": "you"}, {"startTime": "128.500s", "endTime": "128.800s", "word": "met"}, {"startTime": "128.800s", "endTime": "129.100s", "word": "those"}, {"startTime": "129.100s", "endTime": "129.800s", "word": "challenges"}, {"startTime": "130.600s", "endTime": "130.800s", "word": "you"}, {"startTime": "130.800s", "endTime": "131.100s", "word": "did"}, {"startTime": "131.100s", "endTime": "131.300s", "word": "more"}, {"startTime": "131.300s", "endTime": "131.500s", "word": "than"}, {"startTime": "131.500s", "endTime": "131.700s", "word": "just"}, {"startTime": "131.700s", "endTime": "132.300s", "word": "Prevail"}, {"startTime": "132.300s", "endTime": "132.700s", "word": "against"}, {"startTime": "132.700s", "endTime": "133s", "word": "tough"}, {"startTime": "133s", "endTime": "133.600s", "word": "odds"}, {"startTime": "134.200s", "endTime": "134.500s", "word": "you"}, {"startTime": "134.500s", "endTime": "135.600s", "word": "excelled"}]}], "resultEndTime": "135.950s", "languageCode": "en-us"}, {"alternatives": [{"transcript": " yes we've come a long way in 95 Marlboro is barreling along the tracks with the increasing momentum of marble and limited are other premium brands are showing strength as well", "confidence": 0.80510247, "words": [{"startTime": "136.600s", "endTime": "137.100s", "word": "yes"}, {"startTime": "137.700s", "endTime": "137.900s", "word": "we've"}, {"startTime": "137.900s", "endTime": "138s", "word": "come"}, {"startTime": "138s", "endTime": "138.100s", "word": "a"}, {"startTime": "138.100s", "endTime": "138.400s", "word": "long"}, {"startTime": "138.400s", "endTime": "138.600s", "word": "way"}, {"startTime": "138.600s", "endTime": "138.700s", "word": "in"}, {"startTime": "138.700s", "endTime": "139.500s", "word": "95"}, {"startTime": "140.300s", "endTime": "141.100s", "word": "Marlboro"}, {"startTime": "141.100s", "endTime": "141.400s", "word": "is"}, {"startTime": "141.400s", "endTime": "141.900s", "word": "barreling"}, {"startTime": "141.900s", "endTime": "142.300s", "word": "along"}, {"startTime": "142.300s", "endTime": "142.400s", "word": "the"}, {"startTime": "142.400s", "endTime": "143.100s", "word": "tracks"}, {"startTime": "143.500s", "endTime": "143.600s", "word": "with"}, {"startTime": "143.600s", "endTime": "143.800s", "word": "the"}, {"startTime": "143.800s", "endTime": "144.400s", "word": "increasing"}, {"startTime": "144.400s", "endTime": "145s", "word": "momentum"}, {"startTime": "145.100s", "endTime": "145.300s", "word": "of"}, {"startTime": "145.300s", "endTime": "145.700s", "word": "marble"}, {"startTime": "145.700s", "endTime": "145.800s", "word": "and"}, {"startTime": "145.800s", "endTime": "146.400s", "word": "limited"}, {"startTime": "147.200s", "endTime": "147.500s", "word": "are"}, {"startTime": "147.500s", "endTime": "147.700s", "word": "other"}, {"startTime": "147.700s", "endTime": "148.100s", "word": "premium"}, {"startTime": "148.100s", "endTime": "148.600s", "word": "brands"}, {"startTime": "148.700s", "endTime": "148.800s", "word": "are"}, {"startTime": "148.800s", "endTime": "149.200s", "word": "showing"}, {"startTime": "149.200s", "endTime": "149.600s", "word": "strength"}, {"startTime": "149.600s", "endTime": "149.800s", "word": "as"}, {"startTime": "149.800s", "endTime": "150.200s", "word": "well"}]}], "resultEndTime": "150.590s", "languageCode": "en-us"}, {"alternatives": [{"transcript": " and in the discount category our number two brand basic is doing very well", "confidence": 0.81193966, "words": [{"startTime": "151.300s", "endTime": "151.500s", "word": "and"}, {"startTime": "151.500s", "endTime": "151.600s", "word": "in"}, {"startTime": "151.600s", "endTime": "151.700s", "word": "the"}, {"startTime": "151.700s", "endTime": "152.200s", "word": "discount"}, {"startTime": "152.200s", "endTime": "153s", "word": "category"}, {"startTime": "153.200s", "endTime": "153.400s", "word": "our"}, {"startTime": "153.400s", "endTime": "153.700s", "word": "number"}, {"startTime": "153.700s", "endTime": "153.900s", "word": "two"}, {"startTime": "153.900s", "endTime": "154.500s", "word": "brand"}, {"startTime": "154.500s", "endTime": "155.200s", "word": "basic"}, {"startTime": "155.600s", "endTime": "155.800s", "word": "is"}, {"startTime": "155.800s", "endTime": "156.200s", "word": "doing"}, {"startTime": "156.200s", "endTime": "156.500s", "word": "very"}, {"startTime": "156.500s", "endTime": "157s", "word": "well"}]}], "resultEndTime": "157.350s", "languageCode": "en-us"}, {"alternatives": [{"transcript": " since January of 95 Basics category Shear is up 1.5 sharepoint's that's terrific especially when you consider that basic is promoted on image and not on price", "confidence": 0.8146999, "words": [{"startTime": "158.300s", "endTime": "158.600s", "word": "since"}, {"startTime": "158.600s", "endTime": "159.100s", "word": "January"}, {"startTime": "159.100s", "endTime": "159.200s", "word": "of"}, {"startTime": "159.200s", "endTime": "160.200s", "word": "95"}, {"startTime": "160.600s", "endTime": "161.100s", "word": "Basics"}, {"startTime": "161.100s", "endTime": "161.600s", "word": "category"}, {"startTime": "161.600s", "endTime": "162.200s", "word": "Shear"}, {"startTime": "162.500s", "endTime": "162.800s", "word": "is"}, {"startTime": "162.800s", "endTime": "163.300s", "word": "up"}, {"startTime": "163.500s", "endTime": "164.300s", "word": "1.5"}, {"startTime": "164.300s", "endTime": "165.200s", "word": "sharepoint's"}, {"startTime": "165.800s", "endTime": "166.200s", "word": "that's"}, {"startTime": "166.200s", "endTime": "167.100s", "word": "terrific"}, {"startTime": "167.300s", "endTime": "168.200s", "word": "especially"}, {"startTime": "168.400s", "endTime": "168.600s", "word": "when"}, {"startTime": "168.600s", "endTime": "168.700s", "word": "you"}, {"startTime": "168.700s", "endTime": "169.100s", "word": "consider"}, {"startTime": "169.100s", "endTime": "169.300s", "word": "that"}, {"startTime": "169.300s", "endTime": "170s", "word": "basic"}, {"startTime": "170s", "endTime": "170.100s", "word": "is"}, {"startTime": "170.100s", "endTime": "170.700s", "word": "promoted"}, {"startTime": "170.700s", "endTime": "170.900s", "word": "on"}, {"startTime": "170.900s", "endTime": "171.600s", "word": "image"}, {"startTime": "172s", "endTime": "172.200s", "word": "and"}, {"startTime": "172.200s", "endTime": "172.600s", "word": "not"}, {"startTime": "172.600s", "endTime": "172.800s", "word": "on"}, {"startTime": "172.800s", "endTime": "173.300s", "word": "price"}]}], "resultEndTime": "173.830s", "languageCode": "en-us"}, {"alternatives": [{"transcript": " and now 1995 is behind us it's a new year with new opportunities and new challenges", "confidence": 0.9128387, "words": [{"startTime": "174.800s", "endTime": "175s", "word": "and"}, {"startTime": "175s", "endTime": "175.500s", "word": "now"}, {"startTime": "176.200s", "endTime": "177.400s", "word": "1995"}, {"startTime": "177.400s", "endTime": "177.500s", "word": "is"}, {"startTime": "177.500s", "endTime": "178s", "word": "behind"}, {"startTime": "178s", "endTime": "178.400s", "word": "us"}, {"startTime": "179.100s", "endTime": "179.300s", "word": "it's"}, {"startTime": "179.300s", "endTime": "179.300s", "word": "a"}, {"startTime": "179.300s", "endTime": "179.600s", "word": "new"}, {"startTime": "179.600s", "endTime": "180.100s", "word": "year"}, {"startTime": "180.700s", "endTime": "181.100s", "word": "with"}, {"startTime": "181.100s", "endTime": "181.300s", "word": "new"}, {"startTime": "181.300s", "endTime": "182.200s", "word": "opportunities"}, {"startTime": "182.200s", "endTime": "182.400s", "word": "and"}, {"startTime": "182.400s", "endTime": "182.500s", "word": "new"}, {"startTime": "182.500s", "endTime": "183.400s", "word": "challenges"}]}], "resultEndTime": "183.830s", "languageCode": "en-us"}, {"alternatives": [{"transcript": " let me begin 1996 wishing you all a Happy New Year and also by sharing with you some very good news", "confidence": 0.77260673, "words": [{"startTime": "184.500s", "endTime": "184.700s", "word": "let"}, {"startTime": "184.700s", "endTime": "184.800s", "word": "me"}, {"startTime": "184.800s", "endTime": "185.200s", "word": "begin"}, {"startTime": "185.200s", "endTime": "186.500s", "word": "1996"}, {"startTime": "186.800s", "endTime": "187.200s", "word": "wishing"}, {"startTime": "187.200s", "endTime": "187.700s", "word": "you"}, {"startTime": "187.900s", "endTime": "188.600s", "word": "all"}, {"startTime": "188.600s", "endTime": "188.700s", "word": "a"}, {"startTime": "188.700s", "endTime": "189.100s", "word": "Happy"}, {"startTime": "189.100s", "endTime": "189.300s", "word": "New"}, {"startTime": "189.300s", "endTime": "189.800s", "word": "Year"}, {"startTime": "190.600s", "endTime": "190.800s", "word": "and"}, {"startTime": "190.800s", "endTime": "191.400s", "word": "also"}, {"startTime": "191.400s", "endTime": "191.600s", "word": "by"}, {"startTime": "191.600s", "endTime": "192.100s", "word": "sharing"}, {"startTime": "192.100s", "endTime": "192.300s", "word": "with"}, {"startTime": "192.300s", "endTime": "192.700s", "word": "you"}, {"startTime": "193.100s", "endTime": "193.400s", "word": "some"}, {"startTime": "193.400s", "endTime": "193.900s", "word": "very"}, {"startTime": "194s", "endTime": "194.300s", "word": "good"}, {"startTime": "194.300s", "endTime": "195s", "word": "news"}]}], "resultEndTime": "195.370s", "languageCode": "en-us"}, {"alternatives": [{"transcript": " we are introducing basic and three new king size box packings full flavor lights and full flavor menthol", "confidence": 0.9028642, "words": [{"startTime": "197.300s", "endTime": "197.500s", "word": "we"}, {"startTime": "197.500s", "endTime": "197.600s", "word": "are"}, {"startTime": "197.600s", "endTime": "198.300s", "word": "introducing"}, {"startTime": "198.300s", "endTime": "198.900s", "word": "basic"}, {"startTime": "199.200s", "endTime": "199.400s", "word": "and"}, {"startTime": "199.400s", "endTime": "199.700s", "word": "three"}, {"startTime": "199.700s", "endTime": "200.200s", "word": "new"}, {"startTime": "200.200s", "endTime": "200.500s", "word": "king"}, {"startTime": "200.500s", "endTime": "200.900s", "word": "size"}, {"startTime": "200.900s", "endTime": "201.300s", "word": "box"}, {"startTime": "201.300s", "endTime": "202s", "word": "packings"}, {"startTime": "202.600s", "endTime": "202.900s", "word": "full"}, {"startTime": "202.900s", "endTime": "203.500s", "word": "flavor"}, {"startTime": "203.800s", "endTime": "204.500s", "word": "lights"}, {"startTime": "204.800s", "endTime": "205s", "word": "and"}, {"startTime": "205s", "endTime": "205.200s", "word": "full"}, {"startTime": "205.200s", "endTime": "205.500s", "word": "flavor"}, {"startTime": "205.500s", "endTime": "206.100s", "word": "menthol"}]}], "resultEndTime": "206.590s", "languageCode": "en-us"}, {"alternatives": [{"transcript": " basic box will be launched nationally over the next four months", "confidence": 0.9128386, "words": [{"startTime": "207.300s", "endTime": "207.700s", "word": "basic"}, {"startTime": "207.700s", "endTime": "208.200s", "word": "box"}, {"startTime": "208.200s", "endTime": "208.400s", "word": "will"}, {"startTime": "208.400s", "endTime": "208.500s", "word": "be"}, {"startTime": "208.500s", "endTime": "208.900s", "word": "launched"}, {"startTime": "208.900s", "endTime": "209.700s", "word": "nationally"}, {"startTime": "210s", "endTime": "210.200s", "word": "over"}, {"startTime": "210.200s", "endTime": "210.300s", "word": "the"}, {"startTime": "210.300s", "endTime": "210.700s", "word": "next"}, {"startTime": "210.700s", "endTime": "210.900s", "word": "four"}, {"startTime": "210.900s", "endTime": "211.500s", "word": "months"}]}], "resultEndTime": "211.870s", "languageCode": "en-us"}, {"alternatives": [{"transcript": " that's a big box but then basic box is big news", "confidence": 0.9128386, "words": [{"startTime": "212.600s", "endTime": "212.900s", "word": "that's"}, {"startTime": "212.900s", "endTime": "213s", "word": "a"}, {"startTime": "213s", "endTime": "213.300s", "word": "big"}, {"startTime": "213.300s", "endTime": "214s", "word": "box"}, {"startTime": "214.700s", "endTime": "215s", "word": "but"}, {"startTime": "215s", "endTime": "215.500s", "word": "then"}, {"startTime": "215.800s", "endTime": "216.200s", "word": "basic"}, {"startTime": "216.200s", "endTime": "216.900s", "word": "box"}, {"startTime": "217.100s", "endTime": "217.300s", "word": "is"}, {"startTime": "217.300s", "endTime": "217.600s", "word": "big"}, {"startTime": "217.600s", "endTime": "218.200s", "word": "news"}]}], "resultEndTime": "218.580s", "languageCode": "en-us"}, {"alternatives": [{"transcript": " judging from the number of requests we've had for this packing from you the field sales force I know basic box is going to be a welcome addition to the Philip Morris product line", "confidence": 0.9128384, "words": [{"startTime": "219.300s", "endTime": "219.700s", "word": "judging"}, {"startTime": "219.700s", "endTime": "219.800s", "word": "from"}, {"startTime": "219.800s", "endTime": "219.900s", "word": "the"}, {"startTime": "219.900s", "endTime": "220.200s", "word": "number"}, {"startTime": "220.200s", "endTime": "220.300s", "word": "of"}, {"startTime": "220.300s", "endTime": "221.100s", "word": "requests"}, {"startTime": "221.200s", "endTime": "221.400s", "word": "we've"}, {"startTime": "221.400s", "endTime": "221.700s", "word": "had"}, {"startTime": "221.700s", "endTime": "221.800s", "word": "for"}, {"startTime": "221.800s", "endTime": "222.100s", "word": "this"}, {"startTime": "222.100s", "endTime": "222.700s", "word": "packing"}, {"startTime": "223s", "endTime": "223.300s", "word": "from"}, {"startTime": "223.300s", "endTime": "223.400s", "word": "you"}, {"startTime": "223.400s", "endTime": "223.600s", "word": "the"}, {"startTime": "223.600s", "endTime": "223.900s", "word": "field"}, {"startTime": "223.900s", "endTime": "224.300s", "word": "sales"}, {"startTime": "224.300s", "endTime": "224.800s", "word": "force"}, {"startTime": "225.500s", "endTime": "225.700s", "word": "I"}, {"startTime": "225.700s", "endTime": "225.900s", "word": "know"}, {"startTime": "225.900s", "endTime": "226.300s", "word": "basic"}, {"startTime": "226.300s", "endTime": "227s", "word": "box"}, {"startTime": "227.300s", "endTime": "227.400s", "word": "is"}, {"startTime": "227.400s", "endTime": "227.700s", "word": "going"}, {"startTime": "227.700s", "endTime": "227.800s", "word": "to"}, {"startTime": "227.800s", "endTime": "228.100s", "word": "be"}, {"startTime": "228.100s", "endTime": "228.300s", "word": "a"}, {"startTime": "228.300s", "endTime": "229s", "word": "welcome"}, {"startTime": "229s", "endTime": "229.700s", "word": "addition"}, {"startTime": "229.700s", "endTime": "229.800s", "word": "to"}, {"startTime": "229.800s", "endTime": "229.900s", "word": "the"}, {"startTime": "229.900s", "endTime": "230.200s", "word": "Philip"}, {"startTime": "230.200s", "endTime": "230.500s", "word": "Morris"}, {"startTime": "230.500s", "endTime": "230.900s", "word": "product"}, {"startTime": "230.900s", "endTime": "231.400s", "word": "line"}]}], "resultEndTime": "231.790s", "languageCode": "en-us"}, {"alternatives": [{"transcript": " I also know that some of you may be asking why now why basic box first thing out of the gate in the new year", "confidence": 0.8965069, "words": [{"startTime": "232.800s", "endTime": "232.900s", "word": "I"}, {"startTime": "232.900s", "endTime": "233.300s", "word": "also"}, {"startTime": "233.300s", "endTime": "233.500s", "word": "know"}, {"startTime": "233.500s", "endTime": "233.700s", "word": "that"}, {"startTime": "233.700s", "endTime": "233.900s", "word": "some"}, {"startTime": "233.900s", "endTime": "234.100s", "word": "of"}, {"startTime": "234.100s", "endTime": "234.200s", "word": "you"}, {"startTime": "234.200s", "endTime": "234.400s", "word": "may"}, {"startTime": "234.400s", "endTime": "234.600s", "word": "be"}, {"startTime": "234.600s", "endTime": "235.300s", "word": "asking"}, {"startTime": "236.100s", "endTime": "236.400s", "word": "why"}, {"startTime": "236.400s", "endTime": "237s", "word": "now"}, {"startTime": "237.900s", "endTime": "238.300s", "word": "why"}, {"startTime": "238.300s", "endTime": "238.700s", "word": "basic"}, {"startTime": "238.700s", "endTime": "239.300s", "word": "box"}, {"startTime": "239.300s", "endTime": "239.600s", "word": "first"}, {"startTime": "239.600s", "endTime": "240s", "word": "thing"}, {"startTime": "240s", "endTime": "240.100s", "word": "out"}, {"startTime": "240.100s", "endTime": "240.200s", "word": "of"}, {"startTime": "240.200s", "endTime": "240.300s", "word": "the"}, {"startTime": "240.300s", "endTime": "240.800s", "word": "gate"}, {"startTime": "241.200s", "endTime": "241.300s", "word": "in"}, {"startTime": "241.300s", "endTime": "241.400s", "word": "the"}, {"startTime": "241.400s", "endTime": "241.600s", "word": "new"}, {"startTime": "241.600s", "endTime": "242.100s", "word": "year"}]}], "resultEndTime": "242.480s", "languageCode": "en-us"}, {"alternatives": [{"transcript": " I'm here to tell you that I'm absolutely convinced that now is the time for basic box", "confidence": 0.80664027, "words": [{"startTime": "243.500s", "endTime": "243.700s", "word": "I'm"}, {"startTime": "243.700s", "endTime": "244s", "word": "here"}, {"startTime": "244s", "endTime": "244.100s", "word": "to"}, {"startTime": "244.100s", "endTime": "244.400s", "word": "tell"}, {"startTime": "244.400s", "endTime": "244.700s", "word": "you"}, {"startTime": "244.700s", "endTime": "244.900s", "word": "that"}, {"startTime": "244.900s", "endTime": "245.100s", "word": "I'm"}, {"startTime": "245.100s", "endTime": "246s", "word": "absolutely"}, {"startTime": "246s", "endTime": "246.900s", "word": "convinced"}, {"startTime": "247.200s", "endTime": "247.500s", "word": "that"}, {"startTime": "247.500s", "endTime": "248s", "word": "now"}, {"startTime": "248s", "endTime": "248.200s", "word": "is"}, {"startTime": "248.200s", "endTime": "248.300s", "word": "the"}, {"startTime": "248.300s", "endTime": "248.800s", "word": "time"}, {"startTime": "248.900s", "endTime": "249s", "word": "for"}, {"startTime": "249s", "endTime": "249.400s", "word": "basic"}, {"startTime": "249.400s", "endTime": "250s", "word": "box"}]}], "resultEndTime": "250.460s", "languageCode": "en-us"}, {"alternatives": [{"transcript": " there are four reasons", "confidence": 0.88944525, "words": [{"startTime": "251.200s", "endTime": "251.400s", "word": "there"}, {"startTime": "251.400s", "endTime": "251.500s", "word": "are"}, {"startTime": "251.500s", "endTime": "251.800s", "word": "four"}, {"startTime": "251.800s", "endTime": "252.500s", "word": "reasons"}]}], "resultEndTime": "253s", "languageCode": "en-us"}, {"alternatives": [{"transcript": " one take a look at the top 10 brands basic is the only brand in that top 10 without a box packing", "confidence": 0.84315306, "words": [{"startTime": "253.900s", "endTime": "254.400s", "word": "one"}, {"startTime": "255.200s", "endTime": "255.400s", "word": "take"}, {"startTime": "255.400s", "endTime": "255.500s", "word": "a"}, {"startTime": "255.500s", "endTime": "256.100s", "word": "look"}, {"startTime": "256.100s", "endTime": "256.300s", "word": "at"}, {"startTime": "256.300s", "endTime": "256.300s", "word": "the"}, {"startTime": "256.300s", "endTime": "256.600s", "word": "top"}, {"startTime": "256.600s", "endTime": "256.900s", "word": "10"}, {"startTime": "256.900s", "endTime": "257.600s", "word": "brands"}, {"startTime": "258.300s", "endTime": "259s", "word": "basic"}, {"startTime": "259.400s", "endTime": "259.600s", "word": "is"}, {"startTime": "259.600s", "endTime": "259.800s", "word": "the"}, {"startTime": "259.800s", "endTime": "260.100s", "word": "only"}, {"startTime": "260.100s", "endTime": "260.700s", "word": "brand"}, {"startTime": "260.700s", "endTime": "260.900s", "word": "in"}, {"startTime": "260.900s", "endTime": "261.100s", "word": "that"}, {"startTime": "261.100s", "endTime": "261.400s", "word": "top"}, {"startTime": "261.400s", "endTime": "262s", "word": "10"}, {"startTime": "262.500s", "endTime": "263.100s", "word": "without"}, {"startTime": "263.100s", "endTime": "263.100s", "word": "a"}, {"startTime": "263.100s", "endTime": "263.500s", "word": "box"}, {"startTime": "263.500s", "endTime": "264.100s", "word": "packing"}]}], "resultEndTime": "264.550s", "languageCode": "en-us"}, {"alternatives": [{"transcript": " nine out of ten top brands all have box that alone sends a very clear message about the right way to go consumers want a box packing", "confidence": 0.91283846, "words": [{"startTime": "265.300s", "endTime": "265.700s", "word": "nine"}, {"startTime": "265.700s", "endTime": "265.900s", "word": "out"}, {"startTime": "265.900s", "endTime": "266.100s", "word": "of"}, {"startTime": "266.100s", "endTime": "266.500s", "word": "ten"}, {"startTime": "266.500s", "endTime": "266.800s", "word": "top"}, {"startTime": "266.800s", "endTime": "267.500s", "word": "brands"}, {"startTime": "267.700s", "endTime": "268s", "word": "all"}, {"startTime": "268s", "endTime": "268.200s", "word": "have"}, {"startTime": "268.200s", "endTime": "268.800s", "word": "box"}, {"startTime": "269.700s", "endTime": "270.100s", "word": "that"}, {"startTime": "270.100s", "endTime": "270.900s", "word": "alone"}, {"startTime": "271s", "endTime": "271.400s", "word": "sends"}, {"startTime": "271.400s", "endTime": "271.500s", "word": "a"}, {"startTime": "271.500s", "endTime": "271.900s", "word": "very"}, {"startTime": "271.900s", "endTime": "272.200s", "word": "clear"}, {"startTime": "272.200s", "endTime": "272.900s", "word": "message"}, {"startTime": "273s", "endTime": "273.400s", "word": "about"}, {"startTime": "273.400s", "endTime": "273.500s", "word": "the"}, {"startTime": "273.500s", "endTime": "273.900s", "word": "right"}, {"startTime": "273.900s", "endTime": "274s", "word": "way"}, {"startTime": "274s", "endTime": "274.200s", "word": "to"}, {"startTime": "274.200s", "endTime": "274.700s", "word": "go"}, {"startTime": "275.500s", "endTime": "276.400s", "word": "consumers"}, {"startTime": "276.500s", "endTime": "277s", "word": "want"}, {"startTime": "277s", "endTime": "277.100s", "word": "a"}, {"startTime": "277.100s", "endTime": "277.500s", "word": "box"}, {"startTime": "277.500s", "endTime": "278.100s", "word": "packing"}]}], "resultEndTime": "278.580s", "languageCode": "en-us"}, {"alternatives": [{"transcript": " are two major competitors Doral and GPC have box packings however we should note that they don't have box packings and Menthol where they have two strong premium Brands cool and Salem", "confidence": 0.9128384, "words": [{"startTime": "279.600s", "endTime": "279.800s", "word": "are"}, {"startTime": "279.800s", "endTime": "280s", "word": "two"}, {"startTime": "280s", "endTime": "280.300s", "word": "major"}, {"startTime": "280.300s", "endTime": "281.100s", "word": "competitors"}, {"startTime": "281.500s", "endTime": "282.200s", "word": "Doral"}, {"startTime": "282.200s", "endTime": "282.300s", "word": "and"}, {"startTime": "282.300s", "endTime": "283.200s", "word": "GPC"}, {"startTime": "283.800s", "endTime": "284.100s", "word": "have"}, {"startTime": "284.100s", "endTime": "284.300s", "word": "box"}, {"startTime": "284.300s", "endTime": "285s", "word": "packings"}, {"startTime": "285.800s", "endTime": "286.400s", "word": "however"}, {"startTime": "286.500s", "endTime": "286.700s", "word": "we"}, {"startTime": "286.700s", "endTime": "287s", "word": "should"}, {"startTime": "287s", "endTime": "287.600s", "word": "note"}, {"startTime": "288s", "endTime": "288.200s", "word": "that"}, {"startTime": "288.200s", "endTime": "288.300s", "word": "they"}, {"startTime": "288.300s", "endTime": "288.800s", "word": "don't"}, {"startTime": "288.800s", "endTime": "289.100s", "word": "have"}, {"startTime": "289.100s", "endTime": "289.500s", "word": "box"}, {"startTime": "289.500s", "endTime": "290.200s", "word": "packings"}, {"startTime": "290.400s", "endTime": "290.600s", "word": "and"}, {"startTime": "290.600s", "endTime": "291.300s", "word": "Menthol"}, {"startTime": "291.700s", "endTime": "291.900s", "word": "where"}, {"startTime": "291.900s", "endTime": "292.100s", "word": "they"}, {"startTime": "292.100s", "endTime": "292.400s", "word": "have"}, {"startTime": "292.400s", "endTime": "293s", "word": "two"}, {"startTime": "293.100s", "endTime": "293.700s", "word": "strong"}, {"startTime": "293.700s", "endTime": "294.100s", "word": "premium"}, {"startTime": "294.100s", "endTime": "294.800s", "word": "Brands"}, {"startTime": "295.300s", "endTime": "295.900s", "word": "cool"}, {"startTime": "296.300s", "endTime": "296.500s", "word": "and"}, {"startTime": "296.500s", "endTime": "297s", "word": "Salem"}]}], "resultEndTime": "297.480s", "languageCode": "en-us"}, {"alternatives": [{"transcript": " to now is the right time to introduce a new packing to the discount franchise because the overall discount category is continuing to decline", "confidence": 0.8448074, "words": [{"startTime": "298.700s", "endTime": "299.200s", "word": "to"}, {"startTime": "300s", "endTime": "300.300s", "word": "now"}, {"startTime": "300.300s", "endTime": "300.400s", "word": "is"}, {"startTime": "300.400s", "endTime": "300.500s", "word": "the"}, {"startTime": "300.500s", "endTime": "300.800s", "word": "right"}, {"startTime": "300.800s", "endTime": "301.100s", "word": "time"}, {"startTime": "301.100s", "endTime": "301.200s", "word": "to"}, {"startTime": "301.200s", "endTime": "301.800s", "word": "introduce"}, {"startTime": "301.900s", "endTime": "301.900s", "word": "a"}, {"startTime": "301.900s", "endTime": "302.100s", "word": "new"}, {"startTime": "302.100s", "endTime": "302.800s", "word": "packing"}, {"startTime": "303s", "endTime": "303.100s", "word": "to"}, {"startTime": "303.100s", "endTime": "303.200s", "word": "the"}, {"startTime": "303.200s", "endTime": "303.700s", "word": "discount"}, {"startTime": "303.700s", "endTime": "304.600s", "word": "franchise"}, {"startTime": "305.200s", "endTime": "305.600s", "word": "because"}, {"startTime": "305.600s", "endTime": "305.800s", "word": "the"}, {"startTime": "305.800s", "endTime": "306.200s", "word": "overall"}, {"startTime": "306.200s", "endTime": "306.800s", "word": "discount"}, {"startTime": "306.800s", "endTime": "307.500s", "word": "category"}, {"startTime": "307.700s", "endTime": "307.900s", "word": "is"}, {"startTime": "307.900s", "endTime": "308.800s", "word": "continuing"}, {"startTime": "308.900s", "endTime": "309.100s", "word": "to"}, {"startTime": "309.100s", "endTime": "309.700s", "word": "decline"}]}], "resultEndTime": "310.130s", "languageCode": "en-us"}, {"alternatives": [{"transcript": " I'm aware that there are real concerns out there and the argument goes something like this", "confidence": 0.8625842, "words": [{"startTime": "311.100s", "endTime": "311.300s", "word": "I'm"}, {"startTime": "311.300s", "endTime": "311.700s", "word": "aware"}, {"startTime": "311.700s", "endTime": "312s", "word": "that"}, {"startTime": "312s", "endTime": "312.200s", "word": "there"}, {"startTime": "312.200s", "endTime": "312.400s", "word": "are"}, {"startTime": "312.400s", "endTime": "312.800s", "word": "real"}, {"startTime": "312.800s", "endTime": "313.400s", "word": "concerns"}, {"startTime": "313.400s", "endTime": "313.600s", "word": "out"}, {"startTime": "313.600s", "endTime": "314s", "word": "there"}, {"startTime": "314.600s", "endTime": "314.800s", "word": "and"}, {"startTime": "314.800s", "endTime": "314.900s", "word": "the"}, {"startTime": "314.900s", "endTime": "315.500s", "word": "argument"}, {"startTime": "315.500s", "endTime": "315.800s", "word": "goes"}, {"startTime": "315.800s", "endTime": "316.300s", "word": "something"}, {"startTime": "316.300s", "endTime": "316.500s", "word": "like"}, {"startTime": "316.500s", "endTime": "317.100s", "word": "this"}]}], "resultEndTime": "317.510s", "languageCode": "en-us"}, {"alternatives": [{"transcript": " Dave we're a premium based company we can be very successful focusing on the premium side of the business", "confidence": 0.9128387, "words": [{"startTime": "318.700s", "endTime": "319.300s", "word": "Dave"}, {"startTime": "320s", "endTime": "320.100s", "word": "we're"}, {"startTime": "320.100s", "endTime": "320.200s", "word": "a"}, {"startTime": "320.200s", "endTime": "320.600s", "word": "premium"}, {"startTime": "320.600s", "endTime": "320.900s", "word": "based"}, {"startTime": "320.900s", "endTime": "321.500s", "word": "company"}, {"startTime": "322.100s", "endTime": "322.300s", "word": "we"}, {"startTime": "322.300s", "endTime": "322.500s", "word": "can"}, {"startTime": "322.500s", "endTime": "322.700s", "word": "be"}, {"startTime": "322.700s", "endTime": "323.200s", "word": "very"}, {"startTime": "323.200s", "endTime": "324s", "word": "successful"}, {"startTime": "324s", "endTime": "324.800s", "word": "focusing"}, {"startTime": "325s", "endTime": "325.100s", "word": "on"}, {"startTime": "325.100s", "endTime": "325.200s", "word": "the"}, {"startTime": "325.200s", "endTime": "325.600s", "word": "premium"}, {"startTime": "325.600s", "endTime": "325.900s", "word": "side"}, {"startTime": "325.900s", "endTime": "326s", "word": "of"}, {"startTime": "326s", "endTime": "326.100s", "word": "the"}, {"startTime": "326.100s", "endTime": "326.700s", "word": "business"}]}], "resultEndTime": "327.170s", "languageCode": "en-us"}, {"alternatives": [{"transcript": " aren't you afraid this new packing could in fact generate new discount growth", "confidence": 0.91283864, "words": [{"startTime": "327.900s", "endTime": "328.300s", "word": "aren't"}, {"startTime": "328.300s", "endTime": "328.400s", "word": "you"}, {"startTime": "328.400s", "endTime": "329s", "word": "afraid"}, {"startTime": "329s", "endTime": "329.200s", "word": "this"}, {"startTime": "329.200s", "endTime": "329.400s", "word": "new"}, {"startTime": "329.400s", "endTime": "330s", "word": "packing"}, {"startTime": "330s", "endTime": "330.400s", "word": "could"}, {"startTime": "330.400s", "endTime": "330.500s", "word": "in"}, {"startTime": "330.500s", "endTime": "331.200s", "word": "fact"}, {"startTime": "331.200s", "endTime": "331.900s", "word": "generate"}, {"startTime": "332s", "endTime": "332.200s", "word": "new"}, {"startTime": "332.200s", "endTime": "332.700s", "word": "discount"}, {"startTime": "332.700s", "endTime": "333.200s", "word": "growth"}]}], "resultEndTime": "333.620s", "languageCode": "en-us"}, {"alternatives": [{"transcript": " no the fact is that discount box packings have been growing for the past two years within a total category decline so those fears are ungrounded three now is the time for basic box because even in a shrinking discount category we are growing our share", "confidence": 0.87172407, "words": [{"startTime": "334.500s", "endTime": "335.100s", "word": "no"}, {"startTime": "335.600s", "endTime": "335.700s", "word": "the"}, {"startTime": "335.700s", "endTime": "336.300s", "word": "fact"}, {"startTime": "336.300s", "endTime": "336.500s", "word": "is"}, {"startTime": "336.500s", "endTime": "336.800s", "word": "that"}, {"startTime": "336.800s", "endTime": "337.400s", "word": "discount"}, {"startTime": "337.400s", "endTime": "337.700s", "word": "box"}, {"startTime": "337.700s", "endTime": "338.400s", "word": "packings"}, {"startTime": "338.500s", "endTime": "338.700s", "word": "have"}, {"startTime": "338.700s", "endTime": "338.900s", "word": "been"}, {"startTime": "338.900s", "endTime": "339.500s", "word": "growing"}, {"startTime": "339.500s", "endTime": "339.600s", "word": "for"}, {"startTime": "339.600s", "endTime": "339.700s", "word": "the"}, {"startTime": "339.700s", "endTime": "340.200s", "word": "past"}, {"startTime": "340.200s", "endTime": "340.400s", "word": "two"}, {"startTime": "340.400s", "endTime": "340.900s", "word": "years"}, {"startTime": "341.400s", "endTime": "342s", "word": "within"}, {"startTime": "342s", "endTime": "342.200s", "word": "a"}, {"startTime": "342.200s", "endTime": "342.600s", "word": "total"}, {"startTime": "342.600s", "endTime": "343.200s", "word": "category"}, {"startTime": "343.200s", "endTime": "343.900s", "word": "decline"}, {"startTime": "344.900s", "endTime": "345.100s", "word": "so"}, {"startTime": "345.100s", "endTime": "345.500s", "word": "those"}, {"startTime": "345.500s", "endTime": "346.100s", "word": "fears"}, {"startTime": "346.200s", "endTime": "346.700s", "word": "are"}, {"startTime": "346.800s", "endTime": "347.800s", "word": "ungrounded"}, {"startTime": "348.400s", "endTime": "348.900s", "word": "three"}, {"startTime": "349.900s", "endTime": "350.200s", "word": "now"}, {"startTime": "350.200s", "endTime": "350.300s", "word": "is"}, {"startTime": "350.300s", "endTime": "350.400s", "word": "the"}, {"startTime": "350.400s", "endTime": "350.800s", "word": "time"}, {"startTime": "350.800s", "endTime": "350.900s", "word": "for"}, {"startTime": "350.900s", "endTime": "351.300s", "word": "basic"}, {"startTime": "351.300s", "endTime": "351.700s", "word": "box"}, {"startTime": "351.700s", "endTime": "352.200s", "word": "because"}, {"startTime": "352.200s", "endTime": "352.700s", "word": "even"}, {"startTime": "352.700s", "endTime": "352.800s", "word": "in"}, {"startTime": "352.800s", "endTime": "352.900s", "word": "a"}, {"startTime": "352.900s", "endTime": "353.500s", "word": "shrinking"}, {"startTime": "353.500s", "endTime": "354s", "word": "discount"}, {"startTime": "354s", "endTime": "354.700s", "word": "category"}, {"startTime": "355.200s", "endTime": "355.500s", "word": "we"}, {"startTime": "355.500s", "endTime": "355.800s", "word": "are"}, {"startTime": "355.800s", "endTime": "356.200s", "word": "growing"}, {"startTime": "356.200s", "endTime": "356.400s", "word": "our"}, {"startTime": "356.400s", "endTime": "356.900s", "word": "share"}]}], "resultEndTime": "357.280s", "languageCode": "en-us"}, {"alternatives": [{"transcript": " as I said earlier basic is up 1.5 category Shear points since January", "confidence": 0.86130744, "words": [{"startTime": "358.200s", "endTime": "358.400s", "word": "as"}, {"startTime": "358.400s", "endTime": "358.500s", "word": "I"}, {"startTime": "358.500s", "endTime": "358.800s", "word": "said"}, {"startTime": "358.800s", "endTime": "359.400s", "word": "earlier"}, {"startTime": "359.700s", "endTime": "360.100s", "word": "basic"}, {"startTime": "360.100s", "endTime": "360.300s", "word": "is"}, {"startTime": "360.300s", "endTime": "360.700s", "word": "up"}, {"startTime": "360.900s", "endTime": "362s", "word": "1.5"}, {"startTime": "362s", "endTime": "362.600s", "word": "category"}, {"startTime": "362.600s", "endTime": "362.900s", "word": "Shear"}, {"startTime": "362.900s", "endTime": "363.500s", "word": "points"}, {"startTime": "363.500s", "endTime": "363.800s", "word": "since"}, {"startTime": "363.800s", "endTime": "364.500s", "word": "January"}]}], "resultEndTime": "364.970s", "languageCode": "en-us"}, {"alternatives": [{"transcript": " let's not forget that basic is also a major brand its number two in our portfolio only exceeded by the most successful brand in consumer products history more burro", "confidence": 0.80542874, "words": [{"startTime": "365.900s", "endTime": "366.100s", "word": "let's"}, {"startTime": "366.100s", "endTime": "366.400s", "word": "not"}, {"startTime": "366.400s", "endTime": "367s", "word": "forget"}, {"startTime": "367.100s", "endTime": "367.300s", "word": "that"}, {"startTime": "367.300s", "endTime": "367.900s", "word": "basic"}, {"startTime": "367.900s", "endTime": "368.100s", "word": "is"}, {"startTime": "368.100s", "endTime": "368.800s", "word": "also"}, {"startTime": "368.800s", "endTime": "369s", "word": "a"}, {"startTime": "369s", "endTime": "369.400s", "word": "major"}, {"startTime": "369.400s", "endTime": "370s", "word": "brand"}, {"startTime": "370.700s", "endTime": "370.900s", "word": "its"}, {"startTime": "370.900s", "endTime": "371.200s", "word": "number"}, {"startTime": "371.200s", "endTime": "371.600s", "word": "two"}, {"startTime": "371.600s", "endTime": "371.800s", "word": "in"}, {"startTime": "371.800s", "endTime": "372.100s", "word": "our"}, {"startTime": "372.100s", "endTime": "373s", "word": "portfolio"}, {"startTime": "374s", "endTime": "374.400s", "word": "only"}, {"startTime": "374.400s", "endTime": "375.300s", "word": "exceeded"}, {"startTime": "375.500s", "endTime": "375.600s", "word": "by"}, {"startTime": "375.600s", "endTime": "375.800s", "word": "the"}, {"startTime": "375.800s", "endTime": "376.100s", "word": "most"}, {"startTime": "376.100s", "endTime": "376.700s", "word": "successful"}, {"startTime": "376.700s", "endTime": "377.200s", "word": "brand"}, {"startTime": "377.200s", "endTime": "377.400s", "word": "in"}, {"startTime": "377.400s", "endTime": "377.800s", "word": "consumer"}, {"startTime": "377.800s", "endTime": "378.200s", "word": "products"}, {"startTime": "378.200s", "endTime": "378.800s", "word": "history"}, {"startTime": "379.100s", "endTime": "379.300s", "word": "more"}, {"startTime": "379.300s", "endTime": "379.800s", "word": "burro"}]}], "resultEndTime": "380.170s", "languageCode": "en-us"}, {"alternatives": [{"transcript": " yes we are doing great on the premium side let's use that momentum at retail to make basic and even bigger success", "confidence": 0.9128386, "words": [{"startTime": "381.200s", "endTime": "381.800s", "word": "yes"}, {"startTime": "382.200s", "endTime": "382.500s", "word": "we"}, {"startTime": "382.500s", "endTime": "382.700s", "word": "are"}, {"startTime": "382.700s", "endTime": "383s", "word": "doing"}, {"startTime": "383s", "endTime": "383.500s", "word": "great"}, {"startTime": "383.500s", "endTime": "383.600s", "word": "on"}, {"startTime": "383.600s", "endTime": "383.700s", "word": "the"}, {"startTime": "383.700s", "endTime": "384.200s", "word": "premium"}, {"startTime": "384.200s", "endTime": "384.800s", "word": "side"}, {"startTime": "385s", "endTime": "385.400s", "word": "let's"}, {"startTime": "385.400s", "endTime": "385.700s", "word": "use"}, {"startTime": "385.700s", "endTime": "386s", "word": "that"}, {"startTime": "386s", "endTime": "386.400s", "word": "momentum"}, {"startTime": "386.400s", "endTime": "386.600s", "word": "at"}, {"startTime": "386.600s", "endTime": "387s", "word": "retail"}, {"startTime": "387s", "endTime": "387.100s", "word": "to"}, {"startTime": "387.100s", "endTime": "387.500s", "word": "make"}, {"startTime": "387.500s", "endTime": "388s", "word": "basic"}, {"startTime": "388s", "endTime": "388.200s", "word": "and"}, {"startTime": "388.200s", "endTime": "388.600s", "word": "even"}, {"startTime": "388.600s", "endTime": "389s", "word": "bigger"}, {"startTime": "389s", "endTime": "389.800s", "word": "success"}]}], "resultEndTime": "390.270s", "languageCode": "en-us"}, {"alternatives": [{"transcript": " the fact is there are a lot of discount consumers out there who are making purchase decisions based on something other than absolute Rock Bottom price for now is a time for basic box because an absolute sheer Basics performance has been flat we're doing well but Doral and GPC are outpacing us", "confidence": 0.9015618, "words": [{"startTime": "391.100s", "endTime": "391.200s", "word": "the"}, {"startTime": "391.200s", "endTime": "391.700s", "word": "fact"}, {"startTime": "391.700s", "endTime": "392.100s", "word": "is"}, {"startTime": "392.500s", "endTime": "392.800s", "word": "there"}, {"startTime": "392.800s", "endTime": "393.100s", "word": "are"}, {"startTime": "393.100s", "endTime": "393.100s", "word": "a"}, {"startTime": "393.100s", "endTime": "393.700s", "word": "lot"}, {"startTime": "393.700s", "endTime": "393.800s", "word": "of"}, {"startTime": "393.800s", "endTime": "394.300s", "word": "discount"}, {"startTime": "394.300s", "endTime": "395s", "word": "consumers"}, {"startTime": "395s", "endTime": "395.200s", "word": "out"}, {"startTime": "395.200s", "endTime": "395.600s", "word": "there"}, {"startTime": "395.900s", "endTime": "396s", "word": "who"}, {"startTime": "396s", "endTime": "396.100s", "word": "are"}, {"startTime": "396.100s", "endTime": "396.600s", "word": "making"}, {"startTime": "396.600s", "endTime": "397s", "word": "purchase"}, {"startTime": "397s", "endTime": "397.800s", "word": "decisions"}, {"startTime": "398.100s", "endTime": "398.500s", "word": "based"}, {"startTime": "398.500s", "endTime": "398.700s", "word": "on"}, {"startTime": "398.700s", "endTime": "399.300s", "word": "something"}, {"startTime": "399.300s", "endTime": "399.700s", "word": "other"}, {"startTime": "399.900s", "endTime": "400.300s", "word": "than"}, {"startTime": "400.300s", "endTime": "401.200s", "word": "absolute"}, {"startTime": "401.300s", "endTime": "401.700s", "word": "Rock"}, {"startTime": "401.700s", "endTime": "402s", "word": "Bottom"}, {"startTime": "402s", "endTime": "402.700s", "word": "price"}, {"startTime": "403.400s", "endTime": "404s", "word": "for"}, {"startTime": "404.900s", "endTime": "405.200s", "word": "now"}, {"startTime": "405.200s", "endTime": "405.300s", "word": "is"}, {"startTime": "405.300s", "endTime": "405.300s", "word": "a"}, {"startTime": "405.300s", "endTime": "405.600s", "word": "time"}, {"startTime": "405.600s", "endTime": "405.800s", "word": "for"}, {"startTime": "405.800s", "endTime": "406.200s", "word": "basic"}, {"startTime": "406.200s", "endTime": "406.700s", "word": "box"}, {"startTime": "406.800s", "endTime": "407.200s", "word": "because"}, {"startTime": "407.200s", "endTime": "407.400s", "word": "an"}, {"startTime": "407.400s", "endTime": "408s", "word": "absolute"}, {"startTime": "408s", "endTime": "408.500s", "word": "sheer"}, {"startTime": "409s", "endTime": "409.400s", "word": "Basics"}, {"startTime": "409.400s", "endTime": "410.100s", "word": "performance"}, {"startTime": "410.100s", "endTime": "410.500s", "word": "has"}, {"startTime": "410.500s", "endTime": "410.700s", "word": "been"}, {"startTime": "410.700s", "endTime": "411.200s", "word": "flat"}, {"startTime": "412s", "endTime": "412.200s", "word": "we're"}, {"startTime": "412.200s", "endTime": "412.600s", "word": "doing"}, {"startTime": "412.600s", "endTime": "413.100s", "word": "well"}, {"startTime": "413.500s", "endTime": "414.100s", "word": "but"}, {"startTime": "414.300s", "endTime": "414.900s", "word": "Doral"}, {"startTime": "414.900s", "endTime": "415s", "word": "and"}, {"startTime": "415s", "endTime": "415.900s", "word": "GPC"}, {"startTime": "416.100s", "endTime": "416.300s", "word": "are"}, {"startTime": "416.300s", "endTime": "416.900s", "word": "outpacing"}, {"startTime": "416.900s", "endTime": "417.200s", "word": "us"}]}], "resultEndTime": "417.640s", "languageCode": "en-us"}, {"alternatives": [{"transcript": " in a shrinking category these two competitors are growing faster than basic", "confidence": 0.82864547, "words": [{"startTime": "418.400s", "endTime": "418.500s", "word": "in"}, {"startTime": "418.500s", "endTime": "418.600s", "word": "a"}, {"startTime": "418.600s", "endTime": "419s", "word": "shrinking"}, {"startTime": "419s", "endTime": "419.900s", "word": "category"}, {"startTime": "419.900s", "endTime": "420.200s", "word": "these"}, {"startTime": "420.200s", "endTime": "420.400s", "word": "two"}, {"startTime": "420.400s", "endTime": "421.300s", "word": "competitors"}, {"startTime": "421.500s", "endTime": "421.700s", "word": "are"}, {"startTime": "421.700s", "endTime": "422s", "word": "growing"}, {"startTime": "422s", "endTime": "422.700s", "word": "faster"}, {"startTime": "422.900s", "endTime": "423s", "word": "than"}, {"startTime": "423s", "endTime": "423.600s", "word": "basic"}]}], "resultEndTime": "423.980s", "languageCode": "en-us"}, {"alternatives": [{"transcript": " in other words the introduction of basic box is a smart move for the future as well as for right now", "confidence": 0.91228986, "words": [{"startTime": "425.600s", "endTime": "425.900s", "word": "in"}, {"startTime": "425.900s", "endTime": "426.100s", "word": "other"}, {"startTime": "426.100s", "endTime": "426.700s", "word": "words"}, {"startTime": "426.800s", "endTime": "427s", "word": "the"}, {"startTime": "427s", "endTime": "427.800s", "word": "introduction"}, {"startTime": "427.800s", "endTime": "428.100s", "word": "of"}, {"startTime": "428.100s", "endTime": "428.500s", "word": "basic"}, {"startTime": "428.500s", "endTime": "429.200s", "word": "box"}, {"startTime": "429.500s", "endTime": "429.700s", "word": "is"}, {"startTime": "429.700s", "endTime": "429.700s", "word": "a"}, {"startTime": "429.700s", "endTime": "430.200s", "word": "smart"}, {"startTime": "430.200s", "endTime": "430.500s", "word": "move"}, {"startTime": "430.500s", "endTime": "430.600s", "word": "for"}, {"startTime": "430.600s", "endTime": "430.700s", "word": "the"}, {"startTime": "430.700s", "endTime": "431.300s", "word": "future"}, {"startTime": "431.800s", "endTime": "432s", "word": "as"}, {"startTime": "432s", "endTime": "432.200s", "word": "well"}, {"startTime": "432.200s", "endTime": "432.500s", "word": "as"}, {"startTime": "432.500s", "endTime": "432.600s", "word": "for"}, {"startTime": "432.600s", "endTime": "432.900s", "word": "right"}, {"startTime": "432.900s", "endTime": "433.400s", "word": "now"}]}], "resultEndTime": "433.790s", "languageCode": "en-us"}, {"alternatives": [{"transcript": " we've been talking about the why of basic box the next question is how how or are we going to launch this brand", "confidence": 0.79937196, "words": [{"startTime": "435s", "endTime": "435.100s", "word": "we've"}, {"startTime": "435.100s", "endTime": "435.300s", "word": "been"}, {"startTime": "435.300s", "endTime": "435.900s", "word": "talking"}, {"startTime": "435.900s", "endTime": "436.200s", "word": "about"}, {"startTime": "436.200s", "endTime": "436.400s", "word": "the"}, {"startTime": "436.400s", "endTime": "437s", "word": "why"}, {"startTime": "437s", "endTime": "437.100s", "word": "of"}, {"startTime": "437.100s", "endTime": "437.500s", "word": "basic"}, {"startTime": "437.500s", "endTime": "438.100s", "word": "box"}, {"startTime": "439.100s", "endTime": "439.200s", "word": "the"}, {"startTime": "439.200s", "endTime": "439.400s", "word": "next"}, {"startTime": "439.400s", "endTime": "439.900s", "word": "question"}, {"startTime": "439.900s", "endTime": "440.100s", "word": "is"}, {"startTime": "440.400s", "endTime": "441s", "word": "how"}, {"startTime": "441.400s", "endTime": "441.800s", "word": "how"}, {"startTime": "441.800s", "endTime": "442.100s", "word": "or"}, {"startTime": "442.300s", "endTime": "442.400s", "word": "are"}, {"startTime": "442.400s", "endTime": "442.600s", "word": "we"}, {"startTime": "442.600s", "endTime": "442.900s", "word": "going"}, {"startTime": "442.900s", "endTime": "443.100s", "word": "to"}, {"startTime": "443.100s", "endTime": "443.700s", "word": "launch"}, {"startTime": "443.700s", "endTime": "444s", "word": "this"}, {"startTime": "444s", "endTime": "444.500s", "word": "brand"}]}], "resultEndTime": "444.880s", "languageCode": "en-us"}, {"alternatives": [{"transcript": " with a sound strategy and outstanding execution", "confidence": 0.9128385, "words": [{"startTime": "445.700s", "endTime": "445.800s", "word": "with"}, {"startTime": "445.800s", "endTime": "445.900s", "word": "a"}, {"startTime": "445.900s", "endTime": "446.400s", "word": "sound"}, {"startTime": "446.400s", "endTime": "447.200s", "word": "strategy"}, {"startTime": "447.200s", "endTime": "447.500s", "word": "and"}, {"startTime": "447.500s", "endTime": "448.700s", "word": "outstanding"}, {"startTime": "448.800s", "endTime": "449.600s", "word": "execution"}]}], "resultEndTime": "450.030s", "languageCode": "en-us"}, {"alternatives": [{"transcript": " a product launch is unique because you only get one shot at doing it right", "confidence": 0.9128387, "words": [{"startTime": "451.200s", "endTime": "451.300s", "word": "a"}, {"startTime": "451.300s", "endTime": "451.800s", "word": "product"}, {"startTime": "451.800s", "endTime": "452.500s", "word": "launch"}, {"startTime": "452.800s", "endTime": "453s", "word": "is"}, {"startTime": "453s", "endTime": "453.700s", "word": "unique"}, {"startTime": "454.100s", "endTime": "454.400s", "word": "because"}, {"startTime": "454.400s", "endTime": "454.500s", "word": "you"}, {"startTime": "454.500s", "endTime": "454.900s", "word": "only"}, {"startTime": "454.900s", "endTime": "455.200s", "word": "get"}, {"startTime": "455.200s", "endTime": "455.500s", "word": "one"}, {"startTime": "455.500s", "endTime": "456.100s", "word": "shot"}, {"startTime": "456.200s", "endTime": "456.400s", "word": "at"}, {"startTime": "456.400s", "endTime": "456.700s", "word": "doing"}, {"startTime": "456.700s", "endTime": "456.900s", "word": "it"}, {"startTime": "456.900s", "endTime": "457.300s", "word": "right"}]}], "resultEndTime": "457.740s", "languageCode": "en-us"}, {"alternatives": [{"transcript": " let's make the most of this terrific opportunity to seize the attention of consumers and pull competitive smokers into the brand", "confidence": 0.91283864, "words": [{"startTime": "458.400s", "endTime": "458.700s", "word": "let's"}, {"startTime": "458.700s", "endTime": "459s", "word": "make"}, {"startTime": "459s", "endTime": "459.200s", "word": "the"}, {"startTime": "459.200s", "endTime": "459.700s", "word": "most"}, {"startTime": "459.700s", "endTime": "459.800s", "word": "of"}, {"startTime": "459.800s", "endTime": "460.100s", "word": "this"}, {"startTime": "460.100s", "endTime": "460.500s", "word": "terrific"}, {"startTime": "460.500s", "endTime": "461.300s", "word": "opportunity"}, {"startTime": "461.700s", "endTime": "461.900s", "word": "to"}, {"startTime": "461.900s", "endTime": "462.400s", "word": "seize"}, {"startTime": "462.400s", "endTime": "462.500s", "word": "the"}, {"startTime": "462.500s", "endTime": "463.100s", "word": "attention"}, {"startTime": "463.200s", "endTime": "463.300s", "word": "of"}, {"startTime": "463.300s", "endTime": "464.200s", "word": "consumers"}, {"startTime": "464.500s", "endTime": "464.800s", "word": "and"}, {"startTime": "464.800s", "endTime": "465.200s", "word": "pull"}, {"startTime": "465.200s", "endTime": "465.800s", "word": "competitive"}, {"startTime": "465.800s", "endTime": "466.400s", "word": "smokers"}, {"startTime": "466.400s", "endTime": "466.700s", "word": "into"}, {"startTime": "466.700s", "endTime": "466.800s", "word": "the"}, {"startTime": "466.800s", "endTime": "467.300s", "word": "brand"}]}], "resultEndTime": "467.730s", "languageCode": "en-us"}, {"alternatives": [{"transcript": " we plan to make the most of our time right now so we can execute with Excellence from the word go", "confidence": 0.8992742, "words": [{"startTime": "468.600s", "endTime": "468.700s", "word": "we"}, {"startTime": "468.700s", "endTime": "469s", "word": "plan"}, {"startTime": "469s", "endTime": "469.200s", "word": "to"}, {"startTime": "469.200s", "endTime": "469.400s", "word": "make"}, {"startTime": "469.400s", "endTime": "469.500s", "word": "the"}, {"startTime": "469.500s", "endTime": "469.800s", "word": "most"}, {"startTime": "469.800s", "endTime": "469.900s", "word": "of"}, {"startTime": "469.900s", "endTime": "470s", "word": "our"}, {"startTime": "470s", "endTime": "470.600s", "word": "time"}, {"startTime": "470.600s", "endTime": "470.900s", "word": "right"}, {"startTime": "470.900s", "endTime": "471.500s", "word": "now"}, {"startTime": "471.700s", "endTime": "471.900s", "word": "so"}, {"startTime": "471.900s", "endTime": "472s", "word": "we"}, {"startTime": "472s", "endTime": "472.200s", "word": "can"}, {"startTime": "472.200s", "endTime": "472.800s", "word": "execute"}, {"startTime": "472.800s", "endTime": "473s", "word": "with"}, {"startTime": "473s", "endTime": "473.700s", "word": "Excellence"}, {"startTime": "473.800s", "endTime": "474.100s", "word": "from"}, {"startTime": "474.100s", "endTime": "474.200s", "word": "the"}, {"startTime": "474.200s", "endTime": "474.700s", "word": "word"}, {"startTime": "474.700s", "endTime": "475.200s", "word": "go"}]}], "resultEndTime": "475.660s", "languageCode": "en-us"}, {"alternatives": [{"transcript": " when we talked with their consumers the number one thing they tell us is that they want to find the product everywhere", "confidence": 0.84281844, "words": [{"startTime": "476.800s", "endTime": "477s", "word": "when"}, {"startTime": "477s", "endTime": "477.100s", "word": "we"}, {"startTime": "477.100s", "endTime": "477.500s", "word": "talked"}, {"startTime": "477.500s", "endTime": "477.600s", "word": "with"}, {"startTime": "477.600s", "endTime": "477.800s", "word": "their"}, {"startTime": "477.800s", "endTime": "478.600s", "word": "consumers"}, {"startTime": "479.200s", "endTime": "479.300s", "word": "the"}, {"startTime": "479.300s", "endTime": "479.600s", "word": "number"}, {"startTime": "479.600s", "endTime": "479.900s", "word": "one"}, {"startTime": "479.900s", "endTime": "480.200s", "word": "thing"}, {"startTime": "480.200s", "endTime": "480.400s", "word": "they"}, {"startTime": "480.400s", "endTime": "480.700s", "word": "tell"}, {"startTime": "480.700s", "endTime": "481s", "word": "us"}, {"startTime": "481.100s", "endTime": "481.300s", "word": "is"}, {"startTime": "481.300s", "endTime": "481.700s", "word": "that"}, {"startTime": "481.800s", "endTime": "482s", "word": "they"}, {"startTime": "482s", "endTime": "482.100s", "word": "want"}, {"startTime": "482.100s", "endTime": "482.200s", "word": "to"}, {"startTime": "482.200s", "endTime": "482.500s", "word": "find"}, {"startTime": "482.500s", "endTime": "482.600s", "word": "the"}, {"startTime": "482.600s", "endTime": "483.300s", "word": "product"}, {"startTime": "483.300s", "endTime": "484s", "word": "everywhere"}]}], "resultEndTime": "484.410s", "languageCode": "en-us"}, {"alternatives": [{"transcript": " in other words distribution is key our first priority will be to get distribution the goal we've set for ourselves nationally is 80% of anyone packing", "confidence": 0.9128385, "words": [{"startTime": "485.200s", "endTime": "485.400s", "word": "in"}, {"startTime": "485.400s", "endTime": "485.600s", "word": "other"}, {"startTime": "485.600s", "endTime": "486.100s", "word": "words"}, {"startTime": "486.300s", "endTime": "487.300s", "word": "distribution"}, {"startTime": "487.400s", "endTime": "487.700s", "word": "is"}, {"startTime": "487.700s", "endTime": "488.300s", "word": "key"}, {"startTime": "489.500s", "endTime": "489.600s", "word": "our"}, {"startTime": "489.600s", "endTime": "490s", "word": "first"}, {"startTime": "490s", "endTime": "490.700s", "word": "priority"}, {"startTime": "490.900s", "endTime": "491.100s", "word": "will"}, {"startTime": "491.100s", "endTime": "491.200s", "word": "be"}, {"startTime": "491.200s", "endTime": "491.300s", "word": "to"}, {"startTime": "491.300s", "endTime": "491.600s", "word": "get"}, {"startTime": "491.600s", "endTime": "492.500s", "word": "distribution"}, {"startTime": "493.300s", "endTime": "493.500s", "word": "the"}, {"startTime": "493.500s", "endTime": "493.700s", "word": "goal"}, {"startTime": "493.700s", "endTime": "493.900s", "word": "we've"}, {"startTime": "493.900s", "endTime": "494.200s", "word": "set"}, {"startTime": "494.200s", "endTime": "494.300s", "word": "for"}, {"startTime": "494.300s", "endTime": "494.800s", "word": "ourselves"}, {"startTime": "494.800s", "endTime": "495.500s", "word": "nationally"}, {"startTime": "495.700s", "endTime": "496s", "word": "is"}, {"startTime": "496s", "endTime": "497.100s", "word": "80%"}, {"startTime": "497.300s", "endTime": "497.600s", "word": "of"}, {"startTime": "497.600s", "endTime": "498.300s", "word": "anyone"}, {"startTime": "498.300s", "endTime": "498.800s", "word": "packing"}]}], "resultEndTime": "499.210s", "languageCode": "en-us"}, {"alternatives": [{"transcript": " in support of your hard work will be running basic box creative on billboards and magazines during the month of February", "confidence": 0.8435647, "words": [{"startTime": "500.200s", "endTime": "500.300s", "word": "in"}, {"startTime": "500.300s", "endTime": "500.700s", "word": "support"}, {"startTime": "500.700s", "endTime": "500.900s", "word": "of"}, {"startTime": "500.900s", "endTime": "501.100s", "word": "your"}, {"startTime": "501.100s", "endTime": "501.400s", "word": "hard"}, {"startTime": "501.400s", "endTime": "501.900s", "word": "work"}, {"startTime": "502.200s", "endTime": "502.400s", "word": "will"}, {"startTime": "502.400s", "endTime": "502.600s", "word": "be"}, {"startTime": "502.600s", "endTime": "502.900s", "word": "running"}, {"startTime": "502.900s", "endTime": "503.400s", "word": "basic"}, {"startTime": "503.400s", "endTime": "503.700s", "word": "box"}, {"startTime": "503.700s", "endTime": "504.400s", "word": "creative"}, {"startTime": "504.700s", "endTime": "504.900s", "word": "on"}, {"startTime": "504.900s", "endTime": "505.700s", "word": "billboards"}, {"startTime": "505.700s", "endTime": "505.900s", "word": "and"}, {"startTime": "505.900s", "endTime": "506.700s", "word": "magazines"}, {"startTime": "506.700s", "endTime": "507s", "word": "during"}, {"startTime": "507s", "endTime": "507.100s", "word": "the"}, {"startTime": "507.100s", "endTime": "507.300s", "word": "month"}, {"startTime": "507.300s", "endTime": "507.400s", "word": "of"}, {"startTime": "507.400s", "endTime": "508.100s", "word": "February"}]}], "resultEndTime": "508.500s", "languageCode": "en-us"}, {"alternatives": [{"transcript": " as a result we expect consumers to go into the stores and early February asking for the product", "confidence": 0.8830887, "words": [{"startTime": "509.500s", "endTime": "509.600s", "word": "as"}, {"startTime": "509.600s", "endTime": "509.700s", "word": "a"}, {"startTime": "509.700s", "endTime": "510.500s", "word": "result"}, {"startTime": "510.900s", "endTime": "511.100s", "word": "we"}, {"startTime": "511.100s", "endTime": "511.600s", "word": "expect"}, {"startTime": "511.600s", "endTime": "512.300s", "word": "consumers"}, {"startTime": "512.300s", "endTime": "512.400s", "word": "to"}, {"startTime": "512.400s", "endTime": "512.600s", "word": "go"}, {"startTime": "512.600s", "endTime": "512.800s", "word": "into"}, {"startTime": "512.800s", "endTime": "512.900s", "word": "the"}, {"startTime": "512.900s", "endTime": "513.500s", "word": "stores"}, {"startTime": "513.700s", "endTime": "513.900s", "word": "and"}, {"startTime": "513.900s", "endTime": "514.300s", "word": "early"}, {"startTime": "514.300s", "endTime": "515s", "word": "February"}, {"startTime": "515.500s", "endTime": "515.900s", "word": "asking"}, {"startTime": "515.900s", "endTime": "516s", "word": "for"}, {"startTime": "516s", "endTime": "516.100s", "word": "the"}, {"startTime": "516.100s", "endTime": "516.800s", "word": "product"}]}], "resultEndTime": "517.080s", "languageCode": "en-us"}, {"alternatives": [{"transcript": " during the month of February we will be offering a buy two get one free on all soft packings but not on basic Bots we're not putting box in the February promotion because we want to make everyone we want to make sure that everyone has enough time to get distribution", "confidence": 0.8961816, "words": [{"startTime": "518.500s", "endTime": "518.800s", "word": "during"}, {"startTime": "518.800s", "endTime": "518.900s", "word": "the"}, {"startTime": "518.900s", "endTime": "519.100s", "word": "month"}, {"startTime": "519.100s", "endTime": "519.200s", "word": "of"}, {"startTime": "519.200s", "endTime": "519.900s", "word": "February"}, {"startTime": "520.300s", "endTime": "520.400s", "word": "we"}, {"startTime": "520.400s", "endTime": "520.600s", "word": "will"}, {"startTime": "520.600s", "endTime": "520.800s", "word": "be"}, {"startTime": "520.800s", "endTime": "521.400s", "word": "offering"}, {"startTime": "521.400s", "endTime": "521.600s", "word": "a"}, {"startTime": "521.600s", "endTime": "521.900s", "word": "buy"}, {"startTime": "521.900s", "endTime": "522.400s", "word": "two"}, {"startTime": "522.400s", "endTime": "522.700s", "word": "get"}, {"startTime": "522.700s", "endTime": "522.900s", "word": "one"}, {"startTime": "522.900s", "endTime": "523.500s", "word": "free"}, {"startTime": "523.800s", "endTime": "524.100s", "word": "on"}, {"startTime": "524.100s", "endTime": "524.300s", "word": "all"}, {"startTime": "524.300s", "endTime": "524.700s", "word": "soft"}, {"startTime": "524.700s", "endTime": "525.400s", "word": "packings"}, {"startTime": "525.700s", "endTime": "525.900s", "word": "but"}, {"startTime": "525.900s", "endTime": "526.500s", "word": "not"}, {"startTime": "526.500s", "endTime": "526.700s", "word": "on"}, {"startTime": "526.700s", "endTime": "527.100s", "word": "basic"}, {"startTime": "527.100s", "endTime": "527.700s", "word": "Bots"}, {"startTime": "528.600s", "endTime": "528.800s", "word": "we're"}, {"startTime": "528.800s", "endTime": "529s", "word": "not"}, {"startTime": "529s", "endTime": "529.300s", "word": "putting"}, {"startTime": "529.300s", "endTime": "529.800s", "word": "box"}, {"startTime": "529.800s", "endTime": "529.900s", "word": "in"}, {"startTime": "529.900s", "endTime": "529.900s", "word": "the"}, {"startTime": "529.900s", "endTime": "530.400s", "word": "February"}, {"startTime": "530.400s", "endTime": "531.100s", "word": "promotion"}, {"startTime": "531.400s", "endTime": "531.800s", "word": "because"}, {"startTime": "531.800s", "endTime": "531.900s", "word": "we"}, {"startTime": "531.900s", "endTime": "532.100s", "word": "want"}, {"startTime": "532.100s", "endTime": "532.200s", "word": "to"}, {"startTime": "532.200s", "endTime": "532.700s", "word": "make"}, {"startTime": "532.900s", "endTime": "533.700s", "word": "everyone"}, {"startTime": "533.800s", "endTime": "533.900s", "word": "we"}, {"startTime": "533.900s", "endTime": "534s", "word": "want"}, {"startTime": "534s", "endTime": "534.100s", "word": "to"}, {"startTime": "534.100s", "endTime": "534.300s", "word": "make"}, {"startTime": "534.300s", "endTime": "534.900s", "word": "sure"}, {"startTime": "535s", "endTime": "535.200s", "word": "that"}, {"startTime": "535.200s", "endTime": "535.600s", "word": "everyone"}, {"startTime": "535.600s", "endTime": "535.800s", "word": "has"}, {"startTime": "535.800s", "endTime": "536.200s", "word": "enough"}, {"startTime": "536.200s", "endTime": "536.700s", "word": "time"}, {"startTime": "537s", "endTime": "537.200s", "word": "to"}, {"startTime": "537.200s", "endTime": "537.300s", "word": "get"}, {"startTime": "537.300s", "endTime": "538.200s", "word": "distribution"}]}], "resultEndTime": "538.650s", "languageCode": "en-us"}, {"alternatives": [{"transcript": " we'll follow February's promotion with a box specific promotion a buy two get one free for basic box in the first two weeks of March", "confidence": 0.8201296, "words": [{"startTime": "539.600s", "endTime": "539.800s", "word": "we'll"}, {"startTime": "539.800s", "endTime": "540.200s", "word": "follow"}, {"startTime": "540.200s", "endTime": "540.800s", "word": "February's"}, {"startTime": "540.800s", "endTime": "541.500s", "word": "promotion"}, {"startTime": "541.800s", "endTime": "542s", "word": "with"}, {"startTime": "542s", "endTime": "542.100s", "word": "a"}, {"startTime": "542.100s", "endTime": "542.600s", "word": "box"}, {"startTime": "542.600s", "endTime": "543.100s", "word": "specific"}, {"startTime": "543.100s", "endTime": "543.800s", "word": "promotion"}, {"startTime": "544.300s", "endTime": "544.500s", "word": "a"}, {"startTime": "544.500s", "endTime": "544.700s", "word": "buy"}, {"startTime": "544.700s", "endTime": "545.200s", "word": "two"}, {"startTime": "545.200s", "endTime": "545.400s", "word": "get"}, {"startTime": "545.400s", "endTime": "545.600s", "word": "one"}, {"startTime": "545.600s", "endTime": "545.900s", "word": "free"}, {"startTime": "545.900s", "endTime": "546.100s", "word": "for"}, {"startTime": "546.100s", "endTime": "546.500s", "word": "basic"}, {"startTime": "546.500s", "endTime": "547.100s", "word": "box"}, {"startTime": "547.400s", "endTime": "547.400s", "word": "in"}, {"startTime": "547.400s", "endTime": "547.600s", "word": "the"}, {"startTime": "547.600s", "endTime": "547.900s", "word": "first"}, {"startTime": "547.900s", "endTime": "548s", "word": "two"}, {"startTime": "548s", "endTime": "548.300s", "word": "weeks"}, {"startTime": "548.300s", "endTime": "548.400s", "word": "of"}, {"startTime": "548.400s", "endTime": "549s", "word": "March"}]}], "resultEndTime": "549.320s", "languageCode": "en-us"}, {"alternatives": [{"transcript": " in addition will be dropping 60 million buy two get one free coupons in newspapers across the country this will introduce basic box to the smoking public", "confidence": 0.7370034, "words": [{"startTime": "550.200s", "endTime": "550.300s", "word": "in"}, {"startTime": "550.300s", "endTime": "550.800s", "word": "addition"}, {"startTime": "551.300s", "endTime": "551.400s", "word": "will"}, {"startTime": "551.400s", "endTime": "551.600s", "word": "be"}, {"startTime": "551.600s", "endTime": "552.300s", "word": "dropping"}, {"startTime": "552.300s", "endTime": "552.900s", "word": "60"}, {"startTime": "552.900s", "endTime": "553.400s", "word": "million"}, {"startTime": "553.600s", "endTime": "553.900s", "word": "buy"}, {"startTime": "553.900s", "endTime": "554.100s", "word": "two"}, {"startTime": "554.100s", "endTime": "554.400s", "word": "get"}, {"startTime": "554.400s", "endTime": "554.600s", "word": "one"}, {"startTime": "554.600s", "endTime": "554.800s", "word": "free"}, {"startTime": "554.800s", "endTime": "555.600s", "word": "coupons"}, {"startTime": "555.800s", "endTime": "556s", "word": "in"}, {"startTime": "556s", "endTime": "556.800s", "word": "newspapers"}, {"startTime": "557s", "endTime": "557.400s", "word": "across"}, {"startTime": "557.400s", "endTime": "557.500s", "word": "the"}, {"startTime": "557.500s", "endTime": "558.100s", "word": "country"}, {"startTime": "559s", "endTime": "559.200s", "word": "this"}, {"startTime": "559.200s", "endTime": "559.400s", "word": "will"}, {"startTime": "559.400s", "endTime": "559.900s", "word": "introduce"}, {"startTime": "559.900s", "endTime": "560.300s", "word": "basic"}, {"startTime": "560.300s", "endTime": "560.900s", "word": "box"}, {"startTime": "561.100s", "endTime": "561.300s", "word": "to"}, {"startTime": "561.300s", "endTime": "561.300s", "word": "the"}, {"startTime": "561.300s", "endTime": "561.800s", "word": "smoking"}, {"startTime": "561.800s", "endTime": "562.300s", "word": "public"}]}], "resultEndTime": "562.740s", "languageCode": "en-us"}, {"alternatives": [{"transcript": " will also drop three million pieces of mail out to both basic and competitive smokers", "confidence": 0.7949923, "words": [{"startTime": "563.600s", "endTime": "563.800s", "word": "will"}, {"startTime": "563.800s", "endTime": "564.200s", "word": "also"}, {"startTime": "564.200s", "endTime": "564.900s", "word": "drop"}, {"startTime": "564.900s", "endTime": "565.200s", "word": "three"}, {"startTime": "565.200s", "endTime": "565.800s", "word": "million"}, {"startTime": "565.900s", "endTime": "566.300s", "word": "pieces"}, {"startTime": "566.300s", "endTime": "566.400s", "word": "of"}, {"startTime": "566.400s", "endTime": "566.900s", "word": "mail"}, {"startTime": "567.200s", "endTime": "567.400s", "word": "out"}, {"startTime": "567.400s", "endTime": "567.500s", "word": "to"}, {"startTime": "567.500s", "endTime": "567.800s", "word": "both"}, {"startTime": "567.800s", "endTime": "568.500s", "word": "basic"}, {"startTime": "568.600s", "endTime": "568.900s", "word": "and"}, {"startTime": "568.900s", "endTime": "569.400s", "word": "competitive"}, {"startTime": "569.400s", "endTime": "570.100s", "word": "smokers"}]}], "resultEndTime": "570.550s", "languageCode": "en-us"}, {"alternatives": [{"transcript": " it's a fact that we've always supported basic 11 to 12 months out of every year now with basic box we are seizing a terrific opportunity to promote the brand like never before", "confidence": 0.9128384, "words": [{"startTime": "571.700s", "endTime": "571.900s", "word": "it's"}, {"startTime": "571.900s", "endTime": "572s", "word": "a"}, {"startTime": "572s", "endTime": "572.700s", "word": "fact"}, {"startTime": "572.700s", "endTime": "572.900s", "word": "that"}, {"startTime": "572.900s", "endTime": "573.200s", "word": "we've"}, {"startTime": "573.200s", "endTime": "573.600s", "word": "always"}, {"startTime": "573.600s", "endTime": "574s", "word": "supported"}, {"startTime": "574s", "endTime": "574.600s", "word": "basic"}, {"startTime": "574.600s", "endTime": "575.200s", "word": "11"}, {"startTime": "575.600s", "endTime": "575.700s", "word": "to"}, {"startTime": "575.700s", "endTime": "576.100s", "word": "12"}, {"startTime": "576.100s", "endTime": "576.400s", "word": "months"}, {"startTime": "576.400s", "endTime": "576.500s", "word": "out"}, {"startTime": "576.500s", "endTime": "576.600s", "word": "of"}, {"startTime": "576.600s", "endTime": "576.900s", "word": "every"}, {"startTime": "576.900s", "endTime": "577.300s", "word": "year"}, {"startTime": "578.200s", "endTime": "578.500s", "word": "now"}, {"startTime": "578.500s", "endTime": "578.800s", "word": "with"}, {"startTime": "578.800s", "endTime": "579.200s", "word": "basic"}, {"startTime": "579.200s", "endTime": "579.800s", "word": "box"}, {"startTime": "580s", "endTime": "580.200s", "word": "we"}, {"startTime": "580.200s", "endTime": "580.300s", "word": "are"}, {"startTime": "580.300s", "endTime": "580.900s", "word": "seizing"}, {"startTime": "580.900s", "endTime": "581s", "word": "a"}, {"startTime": "581s", "endTime": "581.700s", "word": "terrific"}, {"startTime": "581.700s", "endTime": "582.600s", "word": "opportunity"}, {"startTime": "582.900s", "endTime": "583.100s", "word": "to"}, {"startTime": "583.100s", "endTime": "583.500s", "word": "promote"}, {"startTime": "583.500s", "endTime": "583.600s", "word": "the"}, {"startTime": "583.600s", "endTime": "584.200s", "word": "brand"}, {"startTime": "584.300s", "endTime": "584.600s", "word": "like"}, {"startTime": "584.600s", "endTime": "585.100s", "word": "never"}, {"startTime": "585.200s", "endTime": "585.800s", "word": "before"}]}], "resultEndTime": "586.310s", "languageCode": "en-us"}, {"alternatives": [{"transcript": " we've all heard the expression time is money", "confidence": 0.9128385, "words": [{"startTime": "588s", "endTime": "588.300s", "word": "we've"}, {"startTime": "588.300s", "endTime": "588.600s", "word": "all"}, {"startTime": "588.600s", "endTime": "588.800s", "word": "heard"}, {"startTime": "588.800s", "endTime": "588.900s", "word": "the"}, {"startTime": "588.900s", "endTime": "589.700s", "word": "expression"}, {"startTime": "590.200s", "endTime": "590.600s", "word": "time"}, {"startTime": "590.600s", "endTime": "590.800s", "word": "is"}, {"startTime": "590.800s", "endTime": "591.200s", "word": "money"}]}], "resultEndTime": "591.700s", "languageCode": "en-us"}, {"alternatives": [{"transcript": " let's make the most of our time these first few months of 1996 so that we can be right on the money with basic box time and time again you have demonstrated an ability to successfully meet new challenges now is it time for all of us to begin to make big things happen for basic box", "confidence": 0.9128382, "words": [{"startTime": "592.300s", "endTime": "592.600s", "word": "let's"}, {"startTime": "592.600s", "endTime": "593.200s", "word": "make"}, {"startTime": "593.300s", "endTime": "593.500s", "word": "the"}, {"startTime": "593.500s", "endTime": "594.200s", "word": "most"}, {"startTime": "594.200s", "endTime": "594.300s", "word": "of"}, {"startTime": "594.300s", "endTime": "594.500s", "word": "our"}, {"startTime": "594.500s", "endTime": "594.900s", "word": "time"}, {"startTime": "594.900s", "endTime": "595.200s", "word": "these"}, {"startTime": "595.200s", "endTime": "595.500s", "word": "first"}, {"startTime": "595.500s", "endTime": "595.600s", "word": "few"}, {"startTime": "595.600s", "endTime": "596.200s", "word": "months"}, {"startTime": "596.300s", "endTime": "596.400s", "word": "of"}, {"startTime": "596.400s", "endTime": "597.700s", "word": "1996"}, {"startTime": "598.200s", "endTime": "598.400s", "word": "so"}, {"startTime": "598.400s", "endTime": "598.700s", "word": "that"}, {"startTime": "598.700s", "endTime": "598.800s", "word": "we"}, {"startTime": "598.800s", "endTime": "599s", "word": "can"}, {"startTime": "599s", "endTime": "599.200s", "word": "be"}, {"startTime": "599.200s", "endTime": "599.800s", "word": "right"}, {"startTime": "599.800s", "endTime": "599.900s", "word": "on"}, {"startTime": "599.900s", "endTime": "600s", "word": "the"}, {"startTime": "600s", "endTime": "600.500s", "word": "money"}, {"startTime": "600.600s", "endTime": "600.800s", "word": "with"}, {"startTime": "600.800s", "endTime": "601.200s", "word": "basic"}, {"startTime": "601.200s", "endTime": "601.900s", "word": "box"}, {"startTime": "602.900s", "endTime": "603.400s", "word": "time"}, {"startTime": "603.400s", "endTime": "603.600s", "word": "and"}, {"startTime": "603.600s", "endTime": "603.900s", "word": "time"}, {"startTime": "603.900s", "endTime": "604.500s", "word": "again"}, {"startTime": "604.900s", "endTime": "605.100s", "word": "you"}, {"startTime": "605.100s", "endTime": "605.400s", "word": "have"}, {"startTime": "605.400s", "endTime": "606.400s", "word": "demonstrated"}, {"startTime": "606.500s", "endTime": "606.600s", "word": "an"}, {"startTime": "606.600s", "endTime": "607.300s", "word": "ability"}, {"startTime": "607.600s", "endTime": "607.700s", "word": "to"}, {"startTime": "607.700s", "endTime": "608.700s", "word": "successfully"}, {"startTime": "608.700s", "endTime": "609.300s", "word": "meet"}, {"startTime": "609.300s", "endTime": "609.500s", "word": "new"}, {"startTime": "609.500s", "endTime": "610.400s", "word": "challenges"}, {"startTime": "611.200s", "endTime": "611.600s", "word": "now"}, {"startTime": "611.600s", "endTime": "611.700s", "word": "is"}, {"startTime": "611.700s", "endTime": "611.800s", "word": "it"}, {"startTime": "611.800s", "endTime": "612.200s", "word": "time"}, {"startTime": "612.200s", "endTime": "612.500s", "word": "for"}, {"startTime": "612.500s", "endTime": "612.700s", "word": "all"}, {"startTime": "612.700s", "endTime": "612.900s", "word": "of"}, {"startTime": "612.900s", "endTime": "613.200s", "word": "us"}, {"startTime": "613.600s", "endTime": "613.700s", "word": "to"}, {"startTime": "613.700s", "endTime": "614.100s", "word": "begin"}, {"startTime": "614.100s", "endTime": "614.200s", "word": "to"}, {"startTime": "614.200s", "endTime": "614.700s", "word": "make"}, {"startTime": "614.700s", "endTime": "615s", "word": "big"}, {"startTime": "615s", "endTime": "615.600s", "word": "things"}, {"startTime": "615.600s", "endTime": "616.200s", "word": "happen"}, {"startTime": "616.500s", "endTime": "616.700s", "word": "for"}, {"startTime": "616.700s", "endTime": "617.100s", "word": "basic"}, {"startTime": "617.100s", "endTime": "617.800s", "word": "box"}]}], "resultEndTime": "618.140s", "languageCode": "en-us"}, {"alternatives": [{"transcript": " checking my basic watch I see it's time to turn this over to the host of your meeting who will take you through the specifics of this introduction as it relates to your own sales territory", "confidence": 0.9128384, "words": [{"startTime": "619.800s", "endTime": "620.300s", "word": "checking"}, {"startTime": "620.400s", "endTime": "620.600s", "word": "my"}, {"startTime": "620.600s", "endTime": "621s", "word": "basic"}, {"startTime": "621s", "endTime": "621.700s", "word": "watch"}, {"startTime": "622.100s", "endTime": "622.300s", "word": "I"}, {"startTime": "622.300s", "endTime": "622.500s", "word": "see"}, {"startTime": "622.500s", "endTime": "622.700s", "word": "it's"}, {"startTime": "622.700s", "endTime": "623.100s", "word": "time"}, {"startTime": "623.100s", "endTime": "623.200s", "word": "to"}, {"startTime": "623.200s", "endTime": "623.500s", "word": "turn"}, {"startTime": "623.500s", "endTime": "623.800s", "word": "this"}, {"startTime": "623.800s", "endTime": "624.200s", "word": "over"}, {"startTime": "624.500s", "endTime": "624.600s", "word": "to"}, {"startTime": "624.600s", "endTime": "624.700s", "word": "the"}, {"startTime": "624.700s", "endTime": "625s", "word": "host"}, {"startTime": "625s", "endTime": "625.100s", "word": "of"}, {"startTime": "625.100s", "endTime": "625.300s", "word": "your"}, {"startTime": "625.300s", "endTime": "625.700s", "word": "meeting"}, {"startTime": "626.400s", "endTime": "626.500s", "word": "who"}, {"startTime": "626.500s", "endTime": "626.700s", "word": "will"}, {"startTime": "626.700s", "endTime": "626.900s", "word": "take"}, {"startTime": "626.900s", "endTime": "627s", "word": "you"}, {"startTime": "627s", "endTime": "627.400s", "word": "through"}, {"startTime": "627.400s", "endTime": "627.500s", "word": "the"}, {"startTime": "627.500s", "endTime": "628.400s", "word": "specifics"}, {"startTime": "628.600s", "endTime": "628.700s", "word": "of"}, {"startTime": "628.700s", "endTime": "628.900s", "word": "this"}, {"startTime": "628.900s", "endTime": "629.700s", "word": "introduction"}, {"startTime": "630s", "endTime": "630.100s", "word": "as"}, {"startTime": "630.100s", "endTime": "630.200s", "word": "it"}, {"startTime": "630.200s", "endTime": "630.900s", "word": "relates"}, {"startTime": "631.100s", "endTime": "631.100s", "word": "to"}, {"startTime": "631.100s", "endTime": "631.500s", "word": "your"}, {"startTime": "631.500s", "endTime": "631.800s", "word": "own"}, {"startTime": "631.800s", "endTime": "632.200s", "word": "sales"}, {"startTime": "632.200s", "endTime": "632.900s", "word": "territory"}]}], "resultEndTime": "633.320s", "languageCode": "en-us"}, {"alternatives": [{"transcript": " have a good meeting and good selling", "confidence": 0.9128385, "words": [{"startTime": "634.100s", "endTime": "634.200s", "word": "have"}, {"startTime": "634.200s", "endTime": "634.300s", "word": "a"}, {"startTime": "634.300s", "endTime": "634.600s", "word": "good"}, {"startTime": "634.600s", "endTime": "635.100s", "word": "meeting"}, {"startTime": "635.400s", "endTime": "636s", "word": "and"}, {"startTime": "636.500s", "endTime": "636.800s", "word": "good"}, {"startTime": "636.800s", "endTime": "637.200s", "word": "selling"}]}], "resultEndTime": "637.720s", "languageCode": "en-us"}, {"alternatives": [{}], "resultEndTime": "659.430s", "languageCode": "en-us"}], "totalBilledTime": "750s"}