{"results": [{"alternatives": [{}], "resultEndTime": "4.010s", "languageCode": "en-us"}, {"alternatives": [{}], "resultEndTime": "20.900s", "languageCode": "en-us"}, {"alternatives": [{"transcript": "morning comes to Marlboro Country before the sun does", "confidence": 0.89286107, "words": [{"startTime": "22.700s", "endTime": "23.200s", "word": "morning"}, {"startTime": "23.200s", "endTime": "23.600s", "word": "comes"}, {"startTime": "23.600s", "endTime": "23.700s", "word": "to"}, {"startTime": "23.700s", "endTime": "24.300s", "word": "Marlboro"}, {"startTime": "24.300s", "endTime": "25s", "word": "Country"}, {"startTime": "25.400s", "endTime": "25.700s", "word": "before"}, {"startTime": "25.700s", "endTime": "25.900s", "word": "the"}, {"startTime": "25.900s", "endTime": "26.200s", "word": "sun"}, {"startTime": "26.200s", "endTime": "26.700s", "word": "does"}]}], "resultEndTime": "27.710s", "languageCode": "en-us"}, {"alternatives": [{}], "resultEndTime": "33.910s", "languageCode": "en-us"}, {"alternatives": [{"transcript": " come to where the flavor is come to Marlboro Country", "confidence": 0.9128386, "words": [{"startTime": "41.700s", "endTime": "42s", "word": "come"}, {"startTime": "42s", "endTime": "42.200s", "word": "to"}, {"startTime": "42.200s", "endTime": "42.400s", "word": "where"}, {"startTime": "42.400s", "endTime": "42.500s", "word": "the"}, {"startTime": "42.500s", "endTime": "43s", "word": "flavor"}, {"startTime": "43s", "endTime": "43.600s", "word": "is"}, {"startTime": "44.300s", "endTime": "44.600s", "word": "come"}, {"startTime": "44.600s", "endTime": "45.200s", "word": "to"}, {"startTime": "45.300s", "endTime": "46.100s", "word": "Marlboro"}, {"startTime": "46.100s", "endTime": "46.700s", "word": "Country"}]}], "resultEndTime": "50.540s", "languageCode": "en-us"}], "totalBilledTime": "51s"}